{"version":2,"kind":"Article","sha256":"393774d808de1376730bf501fe376ff76eafa91482b3e26071f4e02376cca8c4","slug":"github-setup-advanced","location":"/foundations/github/github-setup-advanced.md","dependencies":[],"frontmatter":{"title":"Configuring Your GitHub Account","content_includes_title":true,"authors":[{"id":"Project Pythia Community","name":"Project Pythia Community"}],"open_access":true,"license":{"content":{"id":"Apache-2.0","url":"https://opensource.org/licenses/Apache-2.0","name":"Apache License 2.0","free":true,"osi":true},"code":{"id":"CC-BY-4.0","url":"https://creativecommons.org/licenses/by/4.0/","name":"Creative Commons Attribution 4.0 International","free":true,"CC":true}},"github":"https://github.com/projectpythia-mystmd/pythia-foundations","copyright":"2024","abbreviations":{"FOSS":"Free and open-source software","VCS":"Version control system","FTP":"File transfer protocol","TCP":"Transmission Control Protocol"},"numbering":{"title":{"offset":2}},"edit_url":"https://github.com/projectpythia-mystmd/pythia-foundations/blob/main/foundations/github/github-setup-advanced.md","thumbnail":"/pythia-foundations/build/GitHub-logo-59f3015ecd99676d16f9c82487c99775.png","exports":[{"format":"md","filename":"github-setup-advanced.md","url":"/pythia-foundations/build/github-setup-advance-07bb587c34caa160ea01782b29edadab.md"}]},"mdast":{"type":"root","children":[{"type":"block","children":[{"type":"image","url":"/pythia-foundations/build/GitHub-logo-59f3015ecd99676d16f9c82487c99775.png","alt":"GitHub Logo","width":"400px","align":"center","key":"KQFjUodlyB","urlSource":"../../images/GitHub-logo.png"},{"type":"heading","depth":1,"position":{"start":{"line":6,"column":1},"end":{"line":6,"column":1}},"children":[{"type":"text","value":"Configuring Your GitHub Account","position":{"start":{"line":6,"column":1},"end":{"line":6,"column":1}},"key":"J9RWQgQmmT"}],"identifier":"configuring-your-github-account","label":"Configuring Your GitHub Account","html_id":"configuring-your-github-account","implicit":true,"key":"bmC4ONlFUL"},{"type":"heading","depth":2,"position":{"start":{"line":8,"column":1},"end":{"line":8,"column":1}},"children":[{"type":"text","value":"Overview:","position":{"start":{"line":8,"column":1},"end":{"line":8,"column":1}},"key":"jpXhU8ykOM"}],"identifier":"overview","label":"Overview:","html_id":"overview","implicit":true,"key":"JwwjzHa7nT"},{"type":"list","ordered":true,"start":1,"spread":false,"position":{"start":{"line":10,"column":1},"end":{"line":12,"column":1}},"children":[{"type":"listItem","spread":true,"position":{"start":{"line":10,"column":1},"end":{"line":10,"column":1}},"children":[{"type":"text","value":"Configure your GitHub account for secure logins via ssh and/or https","position":{"start":{"line":10,"column":1},"end":{"line":10,"column":1}},"key":"TkkAsazC6v"}],"key":"ksrwt5A7KR"},{"type":"listItem","spread":true,"position":{"start":{"line":11,"column":1},"end":{"line":12,"column":1}},"children":[{"type":"text","value":"Set up notifications on repositories you own or follow","position":{"start":{"line":11,"column":1},"end":{"line":11,"column":1}},"key":"dYocHKiFgk"}],"key":"oYRCVETDFs"}],"key":"I2GoZEPBpD"},{"type":"heading","depth":2,"position":{"start":{"line":13,"column":1},"end":{"line":13,"column":1}},"children":[{"type":"text","value":"Prerequisites","position":{"start":{"line":13,"column":1},"end":{"line":13,"column":1}},"key":"v6OM7I6K91"}],"identifier":"prerequisites","label":"Prerequisites","html_id":"prerequisites","implicit":true,"key":"eOzTfMfQ10"},{"type":"table","position":{"start":{"line":15,"column":1},"end":{"line":20,"column":1}},"children":[{"type":"tableRow","position":{"start":{"line":15,"column":1},"end":{"line":15,"column":1}},"children":[{"type":"tableCell","header":true,"position":{"start":{"line":15,"column":1},"end":{"line":15,"column":1}},"children":[{"type":"text","value":"Concepts","position":{"start":{"line":15,"column":1},"end":{"line":15,"column":1}},"key":"nNbC1C114R"}],"key":"k9U4qtjd8R"},{"type":"tableCell","header":true,"position":{"start":{"line":15,"column":1},"end":{"line":15,"column":1}},"children":[{"type":"text","value":"Importance","position":{"start":{"line":15,"column":1},"end":{"line":15,"column":1}},"key":"Ko8tXKHZY1"}],"key":"CPTQ7XbBng"},{"type":"tableCell","header":true,"position":{"start":{"line":15,"column":1},"end":{"line":15,"column":1}},"children":[{"type":"text","value":"Notes","position":{"start":{"line":15,"column":1},"end":{"line":15,"column":1}},"key":"AAUvf5Y0CO"}],"key":"WZ98RwBcNa"}],"key":"H2NjBKCqTR"},{"type":"tableRow","position":{"start":{"line":17,"column":1},"end":{"line":17,"column":1}},"children":[{"type":"tableCell","position":{"start":{"line":17,"column":1},"end":{"line":17,"column":1}},"children":[{"type":"crossReference","position":{"start":{"line":17,"column":1},"end":{"line":17,"column":1}},"children":[{"type":"text","value":"What is GitHub?","position":{"start":{"line":17,"column":1},"end":{"line":17,"column":1}},"key":"PZk0y7bpI0"}],"identifier":"what-is-github","label":"what-is-github","kind":"heading","template":"{name}","resolved":true,"html_id":"what-is-github","remote":true,"url":"/what-is-github","dataUrl":"/what-is-github.json","key":"bFVxGfuagZ"}],"key":"n3yo1ftASc"},{"type":"tableCell","position":{"start":{"line":17,"column":1},"end":{"line":17,"column":1}},"children":[{"type":"text","value":"Necessary","position":{"start":{"line":17,"column":1},"end":{"line":17,"column":1}},"key":"ojkVKKa4Lk"}],"key":"l6Dff3RFMc"},{"type":"tableCell","position":{"start":{"line":17,"column":1},"end":{"line":17,"column":1}},"children":[{"type":"text","value":"GitHub user account required","position":{"start":{"line":17,"column":1},"end":{"line":17,"column":1}},"key":"VCdu2nskoV"}],"key":"Z7AM3bJAXA"}],"key":"rvXzfB5oGA"},{"type":"tableRow","position":{"start":{"line":18,"column":1},"end":{"line":18,"column":1}},"children":[{"type":"tableCell","position":{"start":{"line":18,"column":1},"end":{"line":18,"column":1}},"children":[{"type":"link","url":"/github-repos","position":{"start":{"line":18,"column":1},"end":{"line":18,"column":1}},"children":[{"type":"text","value":"GitHub Repositories","position":{"start":{"line":18,"column":1},"end":{"line":18,"column":1}},"key":"bakMYrZuvO"}],"urlSource":"github-repos","dataUrl":"/github-repos.json","internal":true,"protocol":"file","key":"Xr7WFPcNna"}],"key":"Lr5zlhESHb"},{"type":"tableCell","position":{"start":{"line":18,"column":1},"end":{"line":18,"column":1}},"children":[{"type":"text","value":"Necessary","position":{"start":{"line":18,"column":1},"end":{"line":18,"column":1}},"key":"cY9BnxPere"}],"key":"abG83XYOcp"},{"type":"tableCell","position":{"start":{"line":18,"column":1},"end":{"line":18,"column":1}},"children":[],"key":"ggGsr6hAbs"}],"key":"sWOch8p1kx"},{"type":"tableRow","position":{"start":{"line":19,"column":1},"end":{"line":19,"column":1}},"children":[{"type":"tableCell","position":{"start":{"line":19,"column":1},"end":{"line":19,"column":1}},"children":[{"type":"link","url":"/github-issues","position":{"start":{"line":19,"column":1},"end":{"line":19,"column":1}},"children":[{"type":"text","value":"Issues and Discussions","position":{"start":{"line":19,"column":1},"end":{"line":19,"column":1}},"key":"FAgQ6EIgi4"}],"urlSource":"github-issues","dataUrl":"/github-issues.json","internal":true,"protocol":"file","key":"KZEpqxRLyo"}],"key":"HOHsgiN1z5"},{"type":"tableCell","position":{"start":{"line":19,"column":1},"end":{"line":19,"column":1}},"children":[{"type":"text","value":"Recommended","position":{"start":{"line":19,"column":1},"end":{"line":19,"column":1}},"key":"DGDIMgkSll"}],"key":"F2blmfdsxl"},{"type":"tableCell","position":{"start":{"line":19,"column":1},"end":{"line":19,"column":1}},"children":[],"key":"xMWC37N8TP"}],"key":"x3BREyDTQ1"},{"type":"tableRow","position":{"start":{"line":20,"column":1},"end":{"line":20,"column":1}},"children":[{"type":"tableCell","position":{"start":{"line":20,"column":1},"end":{"line":20,"column":1}},"children":[{"type":"link","url":"/github-cloning-forking","position":{"start":{"line":20,"column":1},"end":{"line":20,"column":1}},"children":[{"type":"text","value":"Cloning and Forking a Repository","position":{"start":{"line":20,"column":1},"end":{"line":20,"column":1}},"key":"KrBHRs50EU"}],"urlSource":"github-cloning-forking","dataUrl":"/github-cloning-forking.json","internal":true,"protocol":"file","key":"mgKpUC3vIw"}],"key":"oPpUrHRSHd"},{"type":"tableCell","position":{"start":{"line":20,"column":1},"end":{"line":20,"column":1}},"children":[{"type":"text","value":"Recommended","position":{"start":{"line":20,"column":1},"end":{"line":20,"column":1}},"key":"siX25xmKT9"}],"key":"pO3O2SCQNy"},{"type":"tableCell","position":{"start":{"line":20,"column":1},"end":{"line":20,"column":1}},"children":[],"key":"Mto32whEkM"}],"key":"cxOsd8D01l"}],"key":"J1IglNdWzH"},{"type":"list","ordered":false,"spread":false,"position":{"start":{"line":22,"column":1},"end":{"line":23,"column":1}},"children":[{"type":"listItem","spread":true,"position":{"start":{"line":22,"column":1},"end":{"line":23,"column":1}},"children":[{"type":"strong","position":{"start":{"line":22,"column":1},"end":{"line":22,"column":1}},"children":[{"type":"text","value":"Time to learn","position":{"start":{"line":22,"column":1},"end":{"line":22,"column":1}},"key":"rQBCyDMzja"}],"key":"CqRnuCJQGg"},{"type":"text","value":": 35 minutes","position":{"start":{"line":22,"column":1},"end":{"line":22,"column":1}},"key":"rAzNX1d3cw"}],"key":"w4aSw6h1NZ"}],"key":"EbfROU6XhY"},{"type":"thematicBreak","position":{"start":{"line":24,"column":1},"end":{"line":24,"column":1}},"key":"hYf1cnrtDk"},{"type":"heading","depth":2,"position":{"start":{"line":26,"column":1},"end":{"line":26,"column":1}},"children":[{"type":"text","value":"GitHub secure key generation","position":{"start":{"line":26,"column":1},"end":{"line":26,"column":1}},"key":"OhaNyDbNkK"}],"identifier":"github-secure-key-generation","label":"GitHub secure key generation","html_id":"github-secure-key-generation","implicit":true,"key":"VKL16AVhdW"},{"type":"paragraph","position":{"start":{"line":28,"column":1},"end":{"line":28,"column":1}},"children":[{"type":"text","value":"When you signed up for your free account on ","position":{"start":{"line":28,"column":1},"end":{"line":28,"column":1}},"key":"UTWE2oMmjf"},{"type":"link","url":"https://github.com","position":{"start":{"line":28,"column":1},"end":{"line":28,"column":1}},"children":[{"type":"text","value":"GitHub","position":{"start":{"line":28,"column":1},"end":{"line":28,"column":1}},"key":"AYJkE7Ezy8"}],"urlSource":"https://github.com","key":"RMKwMJUWKe"},{"type":"text","value":", you established a ","position":{"start":{"line":28,"column":1},"end":{"line":28,"column":1}},"key":"ffGQiEI2Ds"},{"type":"emphasis","position":{"start":{"line":28,"column":1},"end":{"line":28,"column":1}},"children":[{"type":"text","value":"user ID","position":{"start":{"line":28,"column":1},"end":{"line":28,"column":1}},"key":"SYGKFN0vL8"}],"key":"JnkfVJiEtF"},{"type":"text","value":" and its corresponding ","position":{"start":{"line":28,"column":1},"end":{"line":28,"column":1}},"key":"hj9BZGpKxP"},{"type":"emphasis","position":{"start":{"line":28,"column":1},"end":{"line":28,"column":1}},"children":[{"type":"text","value":"password","position":{"start":{"line":28,"column":1},"end":{"line":28,"column":1}},"key":"cHXNz5HeEJ"}],"key":"RSudG9UMKH"},{"type":"text","value":". Many of the repositories that GitHub serves are readable from anywhere, not even requiring a GitHub account.","position":{"start":{"line":28,"column":1},"end":{"line":28,"column":1}},"key":"YzmRW8ZKwi"}],"key":"YkHOMiFCkX"},{"type":"paragraph","position":{"start":{"line":30,"column":1},"end":{"line":30,"column":1}},"children":[{"type":"text","value":"However, especially when you use the git command-line interface to access a GitHub-hosted repo, there are cases when you need to provide an additional set of login credentials. Some of these cases are:","position":{"start":{"line":30,"column":1},"end":{"line":30,"column":1}},"key":"iE2KMidZWh"}],"key":"gp5JlXeUTy"},{"type":"list","ordered":true,"start":1,"spread":false,"position":{"start":{"line":32,"column":1},"end":{"line":34,"column":1}},"children":[{"type":"listItem","spread":true,"position":{"start":{"line":32,"column":1},"end":{"line":32,"column":1}},"children":[{"type":"text","value":"When you want to clone a ","position":{"start":{"line":32,"column":1},"end":{"line":32,"column":1}},"key":"Xf91K83Bhn"},{"type":"emphasis","position":{"start":{"line":32,"column":1},"end":{"line":32,"column":1}},"children":[{"type":"text","value":"private","position":{"start":{"line":32,"column":1},"end":{"line":32,"column":1}},"key":"gE71wwuL43"}],"key":"vCl3OoZZ0o"},{"type":"text","value":", as opposed to ","position":{"start":{"line":32,"column":1},"end":{"line":32,"column":1}},"key":"IdDNxDorWX"},{"type":"emphasis","position":{"start":{"line":32,"column":1},"end":{"line":32,"column":1}},"children":[{"type":"text","value":"public","position":{"start":{"line":32,"column":1},"end":{"line":32,"column":1}},"key":"zWT1N6uZyh"}],"key":"sStDMQa4IN"},{"type":"text","value":" GitHub repository (","position":{"start":{"line":32,"column":1},"end":{"line":32,"column":1}},"key":"FjYJzEGdXl"},{"type":"strong","position":{"start":{"line":32,"column":1},"end":{"line":32,"column":1}},"children":[{"type":"text","value":"read-access","position":{"start":{"line":32,"column":1},"end":{"line":32,"column":1}},"key":"IV1yZf1oOm"}],"key":"eHce3I1QaM"},{"type":"text","value":")","position":{"start":{"line":32,"column":1},"end":{"line":32,"column":1}},"key":"PCymgcJipm"}],"key":"bDJ5azoECu"},{"type":"listItem","spread":true,"position":{"start":{"line":33,"column":1},"end":{"line":34,"column":1}},"children":[{"type":"text","value":"When you wish to ","position":{"start":{"line":33,"column":1},"end":{"line":33,"column":1}},"key":"j8smeaIqyX"},{"type":"emphasis","position":{"start":{"line":33,"column":1},"end":{"line":33,"column":1}},"children":[{"type":"text","value":"push","position":{"start":{"line":33,"column":1},"end":{"line":33,"column":1}},"key":"k0GQGA9Wiu"}],"key":"bJVmQ0QxFD"},{"type":"text","value":" to a repo (","position":{"start":{"line":33,"column":1},"end":{"line":33,"column":1}},"key":"NrHl8gsuTw"},{"type":"strong","position":{"start":{"line":33,"column":1},"end":{"line":33,"column":1}},"children":[{"type":"text","value":"write-access","position":{"start":{"line":33,"column":1},"end":{"line":33,"column":1}},"key":"gIo23P2tFT"}],"key":"MWhCYJ7EO2"},{"type":"text","value":")","position":{"start":{"line":33,"column":1},"end":{"line":33,"column":1}},"key":"IJMyks0kwc"}],"key":"aLJZ4BSW5t"}],"key":"BUWm6A3vVC"},{"type":"paragraph","position":{"start":{"line":35,"column":1},"end":{"line":35,"column":1}},"children":[{"type":"text","value":"For these use-cases, you won’t be able to simply type your GitHub user ID and password from the command line. Instead, you need to set up ","position":{"start":{"line":35,"column":1},"end":{"line":35,"column":1}},"key":"wocBho92iu"},{"type":"emphasis","position":{"start":{"line":35,"column":1},"end":{"line":35,"column":1}},"children":[{"type":"text","value":"access tokens","position":{"start":{"line":35,"column":1},"end":{"line":35,"column":1}},"key":"JrERZqeHLJ"}],"key":"OgWWmSVVD6"},{"type":"text","value":" that live in two places: in your GitHub account, and in your local computer’s file system.","position":{"start":{"line":35,"column":1},"end":{"line":35,"column":1}},"key":"rcgTzkNzVE"}],"key":"BDhxQ9r4lr"},{"type":"paragraph","position":{"start":{"line":37,"column":1},"end":{"line":37,"column":1}},"children":[{"type":"text","value":"GitHub supports two means of key-based access: via ","position":{"start":{"line":37,"column":1},"end":{"line":37,"column":1}},"key":"u49rEPNLf0"},{"type":"emphasis","position":{"start":{"line":37,"column":1},"end":{"line":37,"column":1}},"children":[{"type":"text","value":"https","position":{"start":{"line":37,"column":1},"end":{"line":37,"column":1}},"key":"XajTqmxapw"}],"key":"Oqe1WTCujn"},{"type":"text","value":", and via ","position":{"start":{"line":37,"column":1},"end":{"line":37,"column":1}},"key":"poKDyxlNwt"},{"type":"emphasis","position":{"start":{"line":37,"column":1},"end":{"line":37,"column":1}},"children":[{"type":"text","value":"ssh","position":{"start":{"line":37,"column":1},"end":{"line":37,"column":1}},"key":"AP6gFVz5Vg"}],"key":"l8VxI4Z2La"},{"type":"text","value":".","position":{"start":{"line":37,"column":1},"end":{"line":37,"column":1}},"key":"bUAobGquGM"}],"key":"nRb6vsSkep"},{"type":"paragraph","position":{"start":{"line":39,"column":1},"end":{"line":39,"column":1}},"children":[{"type":"text","value":"For example, one can clone ","position":{"start":{"line":39,"column":1},"end":{"line":39,"column":1}},"key":"rZgInhx3Ln"},{"type":"link","url":"https://github.com/ProjectPythia/github-sandbox","position":{"start":{"line":39,"column":1},"end":{"line":39,"column":1}},"children":[{"type":"text","value":"Project Pythia’s Sandbox repository","position":{"start":{"line":39,"column":1},"end":{"line":39,"column":1}},"key":"vfEuK7Zjde"}],"urlSource":"https://github.com/ProjectPythia/github-sandbox","error":true,"key":"rDljx6Qx0B"},{"type":"text","value":" using a URL for the https protocol:","position":{"start":{"line":39,"column":1},"end":{"line":39,"column":1}},"key":"aqP9WbRMCZ"}],"key":"Mgzc2Rn8rb"},{"type":"image","url":"/pythia-foundations/build/GitHub_Setup_Advance-6de0c1d62d5c3b00744f40f2a9d092c3.png","alt":"GitHub Clone https","width":"600px","align":"center","key":"e56RnAJ2wy","urlSource":"../../images/GitHub_Setup_Advanced_https_URL.png"},{"type":"thematicBreak","position":{"start":{"line":46,"column":1},"end":{"line":46,"column":1}},"key":"ekXmWdxALZ"},{"type":"paragraph","position":{"start":{"line":48,"column":1},"end":{"line":48,"column":1}},"children":[{"type":"text","value":"The URL in this case is ","position":{"start":{"line":48,"column":1},"end":{"line":48,"column":1}},"key":"JPXih1BkXV"},{"type":"strong","position":{"start":{"line":48,"column":1},"end":{"line":48,"column":1}},"children":[{"type":"link","url":"https://github.com/ProjectPythia/github-sandbox.git","position":{"start":{"line":48,"column":1},"end":{"line":48,"column":1}},"children":[{"type":"text","value":"https://​github​.com​/ProjectPythia​/github​-sandbox​.git","position":{"start":{"line":48,"column":1},"end":{"line":48,"column":1}},"key":"aOvhDyRFhV"}],"urlSource":"https://github.com/ProjectPythia/github-sandbox.git","error":true,"key":"EFo4cnv6Xi"}],"key":"OmTLGz26kK"}],"key":"rRqsuUVj3L"},{"type":"paragraph","position":{"start":{"line":50,"column":1},"end":{"line":50,"column":1}},"children":[{"type":"text","value":"Similarly, if you click on the ","position":{"start":{"line":50,"column":1},"end":{"line":50,"column":1}},"key":"UJwN7bmoVx"},{"type":"strong","position":{"start":{"line":50,"column":1},"end":{"line":50,"column":1}},"children":[{"type":"text","value":"SSH","position":{"start":{"line":50,"column":1},"end":{"line":50,"column":1}},"key":"mVa4QtzDlH"}],"key":"bcOoEXW1RP"},{"type":"text","value":" tab:","position":{"start":{"line":50,"column":1},"end":{"line":50,"column":1}},"key":"qMcyOLPCfs"}],"key":"Gso1dUZXio"},{"type":"image","url":"/pythia-foundations/build/GitHub_Setup_Advance-1df6deb623adb9b0dfdb54ab3d277235.png","alt":"GitHub Clone ssh","width":"600px","align":"center","key":"OvbqOmQlji","urlSource":"../../images/GitHub_Setup_Advanced_ssh_URL.png"},{"type":"thematicBreak","position":{"start":{"line":57,"column":1},"end":{"line":57,"column":1}},"key":"QJkecIlRzJ"},{"type":"paragraph","position":{"start":{"line":59,"column":1},"end":{"line":59,"column":1}},"children":[{"type":"text","value":"Here, the URL is ","position":{"start":{"line":59,"column":1},"end":{"line":59,"column":1}},"key":"cRzOiZ91Jc"},{"type":"strong","position":{"start":{"line":59,"column":1},"end":{"line":59,"column":1}},"children":[{"type":"link","url":"mailto:git@github.com","position":{"start":{"line":59,"column":1},"end":{"line":59,"column":1}},"children":[{"type":"text","value":"git@github.com","position":{"start":{"line":59,"column":1},"end":{"line":59,"column":1}},"key":"sXUn3o70AL"}],"urlSource":"mailto:git@github.com","key":"Odq9B7BbJu"},{"type":"text","value":":ProjectPythia/github-sandbox.git","position":{"start":{"line":59,"column":1},"end":{"line":59,"column":1}},"key":"lssPNsPM0O"}],"key":"aGfYQIOQTw"}],"key":"eQHp04AFbD"},{"type":"heading","depth":2,"position":{"start":{"line":61,"column":1},"end":{"line":61,"column":1}},"children":[{"type":"text","value":"Generate a secure personal access token for https","position":{"start":{"line":61,"column":1},"end":{"line":61,"column":1}},"key":"XyKYPqWBKl"}],"identifier":"generate-a-secure-personal-access-token-for-https","label":"Generate a secure personal access token for https","html_id":"generate-a-secure-personal-access-token-for-https","implicit":true,"key":"Y4eJ5VaPHx"},{"type":"paragraph","position":{"start":{"line":63,"column":1},"end":{"line":63,"column":1}},"children":[{"type":"text","value":"First, you will create a secure token in your GitHub account settings, and then use the token on your local computer.","position":{"start":{"line":63,"column":1},"end":{"line":63,"column":1}},"key":"YsT05igiCs"}],"key":"p78xzomIBm"},{"type":"paragraph","position":{"start":{"line":65,"column":1},"end":{"line":65,"column":1}},"children":[{"type":"text","value":"Follow the steps with helpful screenshots at ","position":{"start":{"line":65,"column":1},"end":{"line":65,"column":1}},"key":"XunbRjoQ8m"},{"type":"link","url":"https://docs.github.com/en/authentication/keeping-your-account-and-data-secure/creating-a-personal-access-token","position":{"start":{"line":65,"column":1},"end":{"line":65,"column":1}},"children":[{"type":"text","value":"GitHub’s PAT Creation","position":{"start":{"line":65,"column":1},"end":{"line":65,"column":1}},"key":"pbpJxhRu8U"}],"urlSource":"https://docs.github.com/en/authentication/keeping-your-account-and-data-secure/creating-a-personal-access-token","key":"zweEBOKPKe"},{"type":"text","value":" page.","position":{"start":{"line":65,"column":1},"end":{"line":65,"column":1}},"key":"iIJwMMwW5m"}],"key":"WSsMoUEMhZ"},{"type":"admonition","children":[{"type":"admonitionTitle","children":[{"type":"text","value":"Tip:","position":{"start":{"line":67,"column":1},"end":{"line":67,"column":1}},"key":"xU06E7eybv"}],"key":"MNVpWvrk51"},{"type":"paragraph","position":{"start":{"line":69,"column":1},"end":{"line":69,"column":1}},"children":[{"type":"text","value":"If using the ","position":{"start":{"line":69,"column":1},"end":{"line":69,"column":1}},"key":"uCx4aPWeCo"},{"type":"emphasis","position":{"start":{"line":69,"column":1},"end":{"line":69,"column":1}},"children":[{"type":"text","value":"https","position":{"start":{"line":69,"column":1},"end":{"line":69,"column":1}},"key":"AFRHe3kcsO"}],"key":"fm9mNA2IDT"},{"type":"text","value":" protocol to ","position":{"start":{"line":69,"column":1},"end":{"line":69,"column":1}},"key":"wubf2P4uxS"},{"type":"emphasis","position":{"start":{"line":69,"column":1},"end":{"line":69,"column":1}},"children":[{"type":"text","value":"push","position":{"start":{"line":69,"column":1},"end":{"line":69,"column":1}},"key":"eAY2GYQ9ww"}],"key":"eYrb9lKfIB"},{"type":"text","value":" to a remote repo, you must have generated and downloaded a personal access token. You ","position":{"start":{"line":69,"column":1},"end":{"line":69,"column":1}},"key":"JJy1tb7dHh"},{"type":"emphasis","position":{"start":{"line":69,"column":1},"end":{"line":69,"column":1}},"children":[{"type":"text","value":"may","position":{"start":{"line":69,"column":1},"end":{"line":69,"column":1}},"key":"GIeG5hl3dV"}],"key":"oXRpcGSu8f"},{"type":"text","value":" also need it when cloning, ","position":{"start":{"line":69,"column":1},"end":{"line":69,"column":1}},"key":"hNwMVmpiDi"},{"type":"emphasis","position":{"start":{"line":69,"column":1},"end":{"line":69,"column":1}},"children":[{"type":"text","value":"if","position":{"start":{"line":69,"column":1},"end":{"line":69,"column":1}},"key":"iEWJwv8eym"}],"key":"zT9Nnm8kL6"},{"type":"text","value":" the remote repo is ","position":{"start":{"line":69,"column":1},"end":{"line":69,"column":1}},"key":"y3d1LHwyBQ"},{"type":"emphasis","position":{"start":{"line":69,"column":1},"end":{"line":69,"column":1}},"children":[{"type":"text","value":"not","position":{"start":{"line":69,"column":1},"end":{"line":69,"column":1}},"key":"AfuuzZcZhW"}],"key":"O1KkVH5bGp"},{"type":"text","value":" open to all.","position":{"start":{"line":69,"column":1},"end":{"line":69,"column":1}},"key":"nrUDtAdvB3"}],"key":"LOnDTPMbKq"}],"class":"tip","key":"NH6erz8p1k"},{"type":"heading","depth":2,"position":{"start":{"line":72,"column":1},"end":{"line":72,"column":1}},"children":[{"type":"text","value":"Generate an SSH public/private keypair","position":{"start":{"line":72,"column":1},"end":{"line":72,"column":1}},"key":"BXTHFr6eoA"}],"identifier":"generate-an-ssh-public-private-keypair","label":"Generate an SSH public/private keypair","html_id":"generate-an-ssh-public-private-keypair","implicit":true,"key":"Vx6hYx5gAc"},{"type":"paragraph","position":{"start":{"line":74,"column":1},"end":{"line":74,"column":1}},"children":[{"type":"text","value":"First, on your local computer, you will create an SSH ","position":{"start":{"line":74,"column":1},"end":{"line":74,"column":1}},"key":"QfRw8VBJL5"},{"type":"emphasis","position":{"start":{"line":74,"column":1},"end":{"line":74,"column":1}},"children":[{"type":"text","value":"public/private keypair","position":{"start":{"line":74,"column":1},"end":{"line":74,"column":1}},"key":"Z0SwXGcN17"}],"key":"H0t1jMZ5WT"},{"type":"text","value":", and then upload the ","position":{"start":{"line":74,"column":1},"end":{"line":74,"column":1}},"key":"D2CZHWVA53"},{"type":"emphasis","position":{"start":{"line":74,"column":1},"end":{"line":74,"column":1}},"children":[{"type":"text","value":"public key","position":{"start":{"line":74,"column":1},"end":{"line":74,"column":1}},"key":"JTNGfeYghA"}],"key":"rjMGFMKgbG"},{"type":"text","value":" to your GitHub account.","position":{"start":{"line":74,"column":1},"end":{"line":74,"column":1}},"key":"f791ki5elC"}],"key":"MwJ80SUtWq"},{"type":"paragraph","position":{"start":{"line":76,"column":1},"end":{"line":76,"column":1}},"children":[{"type":"text","value":"Follow the steps with helpful screenshots at ","position":{"start":{"line":76,"column":1},"end":{"line":76,"column":1}},"key":"aBBmtFR2FS"},{"type":"link","url":"https://docs.github.com/en/github/authenticating-to-github/connecting-to-github-with-ssh","position":{"start":{"line":76,"column":1},"end":{"line":76,"column":1}},"children":[{"type":"text","value":"GitHub’s Connecting to GitHub with SSH","position":{"start":{"line":76,"column":1},"end":{"line":76,"column":1}},"key":"WZPJvCsR6v"}],"urlSource":"https://docs.github.com/en/github/authenticating-to-github/connecting-to-github-with-ssh","key":"rC6eijJqTf"},{"type":"text","value":" page.","position":{"start":{"line":76,"column":1},"end":{"line":76,"column":1}},"key":"KLwVCBbNje"}],"key":"z6shzyGIpM"},{"type":"admonition","children":[{"type":"admonitionTitle","children":[{"type":"text","value":"Tip:","position":{"start":{"line":78,"column":1},"end":{"line":78,"column":1}},"key":"Un9AT1G0La"}],"key":"hV7o8I5EaA"},{"type":"paragraph","position":{"start":{"line":80,"column":1},"end":{"line":80,"column":1}},"children":[{"type":"text","value":"If using the ","position":{"start":{"line":80,"column":1},"end":{"line":80,"column":1}},"key":"URaSoq9VPj"},{"type":"emphasis","position":{"start":{"line":80,"column":1},"end":{"line":80,"column":1}},"children":[{"type":"text","value":"ssh","position":{"start":{"line":80,"column":1},"end":{"line":80,"column":1}},"key":"KkXVnQmRKW"}],"key":"fCGSrFwSFK"},{"type":"text","value":" protocol to clone ","position":{"start":{"line":80,"column":1},"end":{"line":80,"column":1}},"key":"eXNaEqxCGJ"},{"type":"emphasis","position":{"start":{"line":80,"column":1},"end":{"line":80,"column":1}},"children":[{"type":"text","value":"or","position":{"start":{"line":80,"column":1},"end":{"line":80,"column":1}},"key":"czSHWrx239"}],"key":"TXMBV90na7"},{"type":"text","value":" push, you ","position":{"start":{"line":80,"column":1},"end":{"line":80,"column":1}},"key":"l3ROqxk7FH"},{"type":"emphasis","position":{"start":{"line":80,"column":1},"end":{"line":80,"column":1}},"children":[{"type":"text","value":"must","position":{"start":{"line":80,"column":1},"end":{"line":80,"column":1}},"key":"m9DrTj1wrs"}],"key":"flsdhEmfPc"},{"type":"text","value":" have generated and created an ssh key-pair.","position":{"start":{"line":80,"column":1},"end":{"line":80,"column":1}},"key":"JbvdZo635U"}],"key":"HwIwKYZ9dE"}],"class":"tip","key":"LPgPtBlm0Y"},{"type":"thematicBreak","position":{"start":{"line":83,"column":1},"end":{"line":83,"column":1}},"key":"C9SpVkStk3"},{"type":"admonition","children":[{"type":"admonitionTitle","children":[{"type":"text","value":"HTTPS vs SSH: Either is fine!","position":{"start":{"line":85,"column":1},"end":{"line":85,"column":1}},"key":"i2vNpvI2Fi"}],"key":"fFLfOcrQCF"},{"type":"paragraph","position":{"start":{"line":87,"column":1},"end":{"line":87,"column":1}},"children":[{"type":"text","value":"Either ","position":{"start":{"line":87,"column":1},"end":{"line":87,"column":1}},"key":"MXhp80TjXe"},{"type":"strong","position":{"start":{"line":87,"column":1},"end":{"line":87,"column":1}},"children":[{"type":"text","value":"https","position":{"start":{"line":87,"column":1},"end":{"line":87,"column":1}},"key":"SHEg1bHh3P"}],"key":"cNFSaI24Rv"},{"type":"text","value":" or ","position":{"start":{"line":87,"column":1},"end":{"line":87,"column":1}},"key":"iD69aycujk"},{"type":"strong","position":{"start":{"line":87,"column":1},"end":{"line":87,"column":1}},"children":[{"type":"text","value":"ssh","position":{"start":{"line":87,"column":1},"end":{"line":87,"column":1}},"key":"Oh6NifA0On"}],"key":"y6fV2si2Na"},{"type":"text","value":" works fine. Choose whatever you prefer. See ","position":{"start":{"line":87,"column":1},"end":{"line":87,"column":1}},"key":"C8xUPpYpOn"},{"type":"link","url":"https://www.toolsqa.com/git/ssh-protocol/","position":{"start":{"line":87,"column":1},"end":{"line":87,"column":1}},"children":[{"type":"text","value":"this overview","position":{"start":{"line":87,"column":1},"end":{"line":87,"column":1}},"key":"MXjNYPZw20"}],"urlSource":"https://www.toolsqa.com/git/ssh-protocol/","key":"GT7cYGX7hQ"},{"type":"text","value":" of the pros and cons of each protocol.","position":{"start":{"line":87,"column":1},"end":{"line":87,"column":1}},"key":"EidLawbhBd"}],"key":"D9eb12pqS8"}],"class":"note","key":"WD90rGRMaj"},{"type":"thematicBreak","position":{"start":{"line":90,"column":1},"end":{"line":90,"column":1}},"key":"s1WKj1GIop"},{"type":"heading","depth":2,"position":{"start":{"line":92,"column":1},"end":{"line":92,"column":1}},"children":[{"type":"text","value":"GitHub notifications","position":{"start":{"line":92,"column":1},"end":{"line":92,"column":1}},"key":"oK2mTTF9xQ"}],"identifier":"github-notifications","label":"GitHub notifications","html_id":"github-notifications","implicit":true,"key":"m76TutgidO"},{"type":"paragraph","position":{"start":{"line":94,"column":1},"end":{"line":94,"column":1}},"children":[{"type":"text","value":"In keeping with the social network aspect of GitHub, you can ","position":{"start":{"line":94,"column":1},"end":{"line":94,"column":1}},"key":"vTRrSwUIbY"},{"type":"emphasis","position":{"start":{"line":94,"column":1},"end":{"line":94,"column":1}},"children":[{"type":"text","value":"follow","position":{"start":{"line":94,"column":1},"end":{"line":94,"column":1}},"key":"E2BXydCs1a"}],"key":"ihO6J86c3p"},{"type":"text","value":" particular repositories that are of interest to you. Additionally, once you begin contributing to a repository, you may wish to be notified when Pull Requests are made, Issues are posted, your code review is requested, and so on. While it’s easy to have GitHub email you at the address you used when you registered for your GitHub account, you may wish to avoid email clutter.","position":{"start":{"line":94,"column":1},"end":{"line":94,"column":1}},"key":"w1iIimLtZz"}],"key":"R1HTBFUxdA"},{"type":"heading","depth":3,"position":{"start":{"line":96,"column":1},"end":{"line":96,"column":1}},"children":[{"type":"text","value":"Email notifications","position":{"start":{"line":96,"column":1},"end":{"line":96,"column":1}},"key":"csw002LRdn"}],"identifier":"email-notifications","label":"Email notifications","html_id":"email-notifications","implicit":true,"key":"kDG6bXJnxi"},{"type":"paragraph","position":{"start":{"line":98,"column":1},"end":{"line":98,"column":1}},"children":[{"type":"text","value":"Let’s say you wish to monitor (or ","position":{"start":{"line":98,"column":1},"end":{"line":98,"column":1}},"key":"xNtoFiEnsx"},{"type":"emphasis","position":{"start":{"line":98,"column":1},"end":{"line":98,"column":1}},"children":[{"type":"text","value":"watch","position":{"start":{"line":98,"column":1},"end":{"line":98,"column":1}},"key":"eZp5GqLdE2"}],"key":"dF1SvPHBOW"},{"type":"text","value":") the Project Pythia GitHub Sandbox repository and receive emails about it.","position":{"start":{"line":98,"column":1},"end":{"line":98,"column":1}},"key":"Hklcek5ZYV"}],"key":"HseRo3ZKLs"},{"type":"paragraph","position":{"start":{"line":100,"column":1},"end":{"line":100,"column":1}},"children":[{"type":"text","value":"Click on the ","position":{"start":{"line":100,"column":1},"end":{"line":100,"column":1}},"key":"TRVk4Vnv6M"},{"type":"strong","position":{"start":{"line":100,"column":1},"end":{"line":100,"column":1}},"children":[{"type":"text","value":"Watch","position":{"start":{"line":100,"column":1},"end":{"line":100,"column":1}},"key":"EytsY77oOe"}],"key":"oJDaNJ0W7q"},{"type":"text","value":" link near the top of the page:","position":{"start":{"line":100,"column":1},"end":{"line":100,"column":1}},"key":"mhogL8EoBV"}],"key":"JPEgOWuPqv"},{"type":"image","url":"/pythia-foundations/build/GitHub_Setup_Advance-7f89889417433ebd4867fdc9801bb463.png","alt":"GitHub Watch","width":"600px","align":"center","key":"tvC6tMP8nJ","urlSource":"../../images/GitHub_Setup_Advanced_Watch.png"},{"type":"thematicBreak","position":{"start":{"line":107,"column":1},"end":{"line":107,"column":1}},"key":"Rplo5b9cSs"},{"type":"paragraph","position":{"start":{"line":109,"column":1},"end":{"line":109,"column":1}},"children":[{"type":"text","value":"You can then select what type of notifications you wish to receive. For example, you may want to receive ","position":{"start":{"line":109,"column":1},"end":{"line":109,"column":1}},"key":"GUH1lazCja"},{"type":"emphasis","position":{"start":{"line":109,"column":1},"end":{"line":109,"column":1}},"children":[{"type":"text","value":"all notifications","position":{"start":{"line":109,"column":1},"end":{"line":109,"column":1}},"key":"zga1u3AmZ1"}],"key":"MF0vS2lItq"},{"type":"text","value":" related to that repo:","position":{"start":{"line":109,"column":1},"end":{"line":109,"column":1}},"key":"Z1L3Himv5I"}],"key":"z3BqGERlUp"},{"type":"image","url":"/pythia-foundations/build/GitHub_Setup_Advance-ee7efdcdb0b22f5e120effe6bb552dab.png","alt":"GitHub Watch All Activity","width":"600px","align":"center","key":"l0YzCIyCOu","urlSource":"../../images/GitHub_Setup_Advanced_Watch_All_Activity.png"},{"type":"thematicBreak","position":{"start":{"line":116,"column":1},"end":{"line":116,"column":1}},"key":"oGdReXvu7T"},{"type":"paragraph","position":{"start":{"line":118,"column":1},"end":{"line":118,"column":1}},"children":[{"type":"text","value":"You will then receive email at the address you used when you signed up for GitHub whenever activity occurs on that repo.","position":{"start":{"line":118,"column":1},"end":{"line":118,"column":1}},"key":"svdHzIe2Vi"}],"key":"zENgcyH4hC"},{"type":"image","url":"/pythia-foundations/build/GitHub_Setup_Advance-13830425ee2c90dc63aea0df795ee0a2.png","alt":"GitHub Unwatch","width":"600px","align":"center","key":"PEep9hWhjn","urlSource":"../../images/GitHub_Setup_Advanced_Unwatch.png"},{"type":"thematicBreak","position":{"start":{"line":125,"column":1},"end":{"line":125,"column":1}},"key":"HaGWgUc55r"},{"type":"paragraph","position":{"start":{"line":127,"column":1},"end":{"line":127,"column":1}},"children":[{"type":"text","value":"You can stop watching that repo by just clicking on the now-labeled ","position":{"start":{"line":127,"column":1},"end":{"line":127,"column":1}},"key":"nw3deqZldm"},{"type":"emphasis","position":{"start":{"line":127,"column":1},"end":{"line":127,"column":1}},"children":[{"type":"text","value":"Unwatch","position":{"start":{"line":127,"column":1},"end":{"line":127,"column":1}},"key":"bdFr2jC59e"}],"key":"qEO9w35R9I"},{"type":"text","value":" link again, and choosing _Participating and ","position":{"start":{"line":127,"column":1},"end":{"line":127,"column":1}},"key":"wScBX5kv18"},{"type":"cite","identifier":"mentions_","label":"mentions_","kind":"narrative","position":{"start":{"line":127,"column":123},"end":{"line":127,"column":133}},"error":"not found","key":"IGZZsNbrmb"},{"type":"text","value":" to toggle it back to ","position":{"start":{"line":127,"column":1},"end":{"line":127,"column":1}},"key":"tBhE0nygRf"},{"type":"emphasis","position":{"start":{"line":127,"column":1},"end":{"line":127,"column":1}},"children":[{"type":"text","value":"Unwatch","position":{"start":{"line":127,"column":1},"end":{"line":127,"column":1}},"key":"kIjiwjjPWd"}],"key":"AWYYcMjezd"},{"type":"text","value":".","position":{"start":{"line":127,"column":1},"end":{"line":127,"column":1}},"key":"sjDFmDTu0R"}],"key":"CYjjNVA5uw"},{"type":"heading","depth":2,"position":{"start":{"line":129,"column":1},"end":{"line":129,"column":1}},"children":[{"type":"text","value":"Stop spamming me, GitHub!","position":{"start":{"line":129,"column":1},"end":{"line":129,"column":1}},"key":"L2gYeriqmQ"}],"identifier":"stop-spamming-me-github","label":"Stop spamming me, GitHub!","html_id":"stop-spamming-me-github","implicit":true,"key":"yq1KQ8352l"},{"type":"paragraph","position":{"start":{"line":131,"column":1},"end":{"line":132,"column":1}},"children":[{"type":"text","value":"It’s easy to become overwhelmed with email from one or more repos that you are following and/or participating in! In this case, you may wish to disable email notifications.\nIn order to set your notification settings, go to ","position":{"start":{"line":131,"column":1},"end":{"line":131,"column":1}},"key":"B1u8vpsws5"},{"type":"strong","position":{"start":{"line":131,"column":1},"end":{"line":131,"column":1}},"children":[{"type":"link","url":"https://github.com/settings/notifications","position":{"start":{"line":131,"column":1},"end":{"line":131,"column":1}},"children":[{"type":"text","value":"https://​github​.com​/settings​/notifications","position":{"start":{"line":131,"column":1},"end":{"line":131,"column":1}},"key":"wN2u9uAjzn"}],"urlSource":"https://github.com/settings/notifications","error":true,"key":"G1AQ0Ux3vp"}],"key":"bOXUsBIGD2"},{"type":"text","value":". You can, for example, uncheck the ","position":{"start":{"line":131,"column":1},"end":{"line":131,"column":1}},"key":"dOHAWIqhi3"},{"type":"strong","position":{"start":{"line":131,"column":1},"end":{"line":131,"column":1}},"children":[{"type":"text","value":"Email","position":{"start":{"line":131,"column":1},"end":{"line":131,"column":1}},"key":"yZ75EOSnDy"}],"key":"aezSJbzgGZ"},{"type":"text","value":" boxes to cease receiving notifications that way:","position":{"start":{"line":131,"column":1},"end":{"line":131,"column":1}},"key":"xfuR4VGazR"}],"key":"PjPwcwHHbR"},{"type":"image","url":"/pythia-foundations/build/GitHub_Setup_Advance-5c7b338c4f5b688659cc676b49bca055.png","alt":"GitHub Notification Settings","width":"600px","align":"center","key":"zm0Rpaz63g","urlSource":"../../images/GitHub_Setup_Advanced_Notification_Settings.png"},{"type":"thematicBreak","position":{"start":{"line":139,"column":1},"end":{"line":139,"column":1}},"key":"xT9yw18C2H"},{"type":"paragraph","position":{"start":{"line":141,"column":1},"end":{"line":141,"column":1}},"children":[{"type":"text","value":"If you turn email notifications off, get in the habit of clicking on the ","position":{"start":{"line":141,"column":1},"end":{"line":141,"column":1}},"key":"hjBqVcx5Df"},{"type":"emphasis","position":{"start":{"line":141,"column":1},"end":{"line":141,"column":1}},"children":[{"type":"text","value":"Notifications","position":{"start":{"line":141,"column":1},"end":{"line":141,"column":1}},"key":"v4Al5MViNm"}],"key":"z1BXMditIJ"},{"type":"text","value":" icon when logged into GitHub:","position":{"start":{"line":141,"column":1},"end":{"line":141,"column":1}},"key":"qQRYtR0ZRE"}],"key":"PvseahuaI3"},{"type":"image","url":"/pythia-foundations/build/GitHub_Setup_Advance-053b8e93939625fb9e5ad7870d3475ee.png","alt":"GitHub Notifications","width":"600px","align":"center","key":"xZbdJUu4f8","urlSource":"../../images/GitHub_Setup_Advanced_Notifications.png"},{"type":"thematicBreak","position":{"start":{"line":148,"column":1},"end":{"line":148,"column":1}},"key":"LZFAk3T033"},{"type":"paragraph","position":{"start":{"line":150,"column":1},"end":{"line":150,"column":1}},"children":[{"type":"text","value":"You can click on the ","position":{"start":{"line":150,"column":1},"end":{"line":150,"column":1}},"key":"XlMpEy5oUE"},{"type":"emphasis","position":{"start":{"line":150,"column":1},"end":{"line":150,"column":1}},"children":[{"type":"text","value":"Notifications","position":{"start":{"line":150,"column":1},"end":{"line":150,"column":1}},"key":"WyvVJuccvq"}],"key":"EnX4oD4wsb"},{"type":"text","value":" icon and scroll through all notifications from repos that you opted into receiving notifications from:","position":{"start":{"line":150,"column":1},"end":{"line":150,"column":1}},"key":"YWjKEkzs8j"}],"key":"A3aZSS9siT"},{"type":"image","url":"/pythia-foundations/build/GitHub_Setup_Advance-84e552da81b4d1ab25c889ad9d25ef65.png","alt":"GitHub Notification Browser","width":"600px","align":"center","key":"g9QGf5uFkJ","urlSource":"../../images/GitHub_Setup_Advanced_Notifications_Browser.png"},{"type":"thematicBreak","position":{"start":{"line":157,"column":1},"end":{"line":157,"column":1}},"key":"N4wL35or7p"},{"type":"paragraph","position":{"start":{"line":159,"column":1},"end":{"line":159,"column":1}},"children":[{"type":"text","value":"Use the ","position":{"start":{"line":159,"column":1},"end":{"line":159,"column":1}},"key":"dVFprw6xh6"},{"type":"emphasis","position":{"start":{"line":159,"column":1},"end":{"line":159,"column":1}},"children":[{"type":"text","value":"Filter notifications","position":{"start":{"line":159,"column":1},"end":{"line":159,"column":1}},"key":"FHElJGeKnq"}],"key":"X4SsIlMPos"},{"type":"text","value":" control to display only those that meet certain criteria. For example, say you only wanted to view topics related to the ","position":{"start":{"line":159,"column":1},"end":{"line":159,"column":1}},"key":"qbFOfVB2i7"},{"type":"emphasis","position":{"start":{"line":159,"column":1},"end":{"line":159,"column":1}},"children":[{"type":"text","value":"MetPy","position":{"start":{"line":159,"column":1},"end":{"line":159,"column":1}},"key":"WFsO0vnUvM"}],"key":"SZTz5c3YJh"},{"type":"text","value":" repo:","position":{"start":{"line":159,"column":1},"end":{"line":159,"column":1}},"key":"jUh52WMm8Q"}],"key":"vdZ8Ooddli"},{"type":"image","url":"/pythia-foundations/build/GitHub_Setup_Advance-e21c2a2740f4b726b39bc83859a13e0c.png","alt":"GitHub Notification Filter","width":"600px","align":"center","key":"r8WRCDLnbW","urlSource":"../../images/GitHub_Setup_Advanced_Notification_Filter.png"},{"type":"thematicBreak","position":{"start":{"line":166,"column":1},"end":{"line":166,"column":1}},"key":"acN0dNzotg"},{"type":"admonition","children":[{"type":"admonitionTitle","children":[{"type":"text","value":"Tip:","position":{"start":{"line":168,"column":1},"end":{"line":168,"column":1}},"key":"sbD2Z8248R"}],"key":"Pzm9Chsr7C"},{"type":"paragraph","position":{"start":{"line":170,"column":1},"end":{"line":170,"column":1}},"children":[{"type":"text","value":"In the list of notifications, you can unsubscribe as shown below.","position":{"start":{"line":170,"column":1},"end":{"line":170,"column":1}},"key":"uJRK8HUcSo"}],"key":"bmbwFb2zCE"}],"class":"tip","key":"hohRTuyjTV"},{"type":"image","url":"/pythia-foundations/build/GitHub_Setup_Advance-79fb444b91f9aecd105d4b99ce4d4f24.png","alt":"GitHub Notification Unsubscribe","width":"600px","align":"center","key":"Y4L9jOo0E4","urlSource":"../../images/GitHub_Setup_Advanced_Notifications_Unsubscribe.png"},{"type":"thematicBreak","position":{"start":{"line":178,"column":1},"end":{"line":178,"column":1}},"key":"yyhTjGj6AM"},{"type":"heading","depth":2,"position":{"start":{"line":180,"column":1},"end":{"line":180,"column":1}},"children":[{"type":"text","value":"Summary","position":{"start":{"line":180,"column":1},"end":{"line":180,"column":1}},"key":"fmO5wZWCkR"}],"identifier":"summary","label":"Summary","html_id":"summary","implicit":true,"key":"SKyvFWiWzN"},{"type":"list","ordered":false,"spread":false,"position":{"start":{"line":182,"column":1},"end":{"line":184,"column":1}},"children":[{"type":"listItem","spread":true,"position":{"start":{"line":182,"column":1},"end":{"line":182,"column":1}},"children":[{"type":"text","value":"GitHub uses ","position":{"start":{"line":182,"column":1},"end":{"line":182,"column":1}},"key":"Mnpnq7DsPY"},{"type":"strong","position":{"start":{"line":182,"column":1},"end":{"line":182,"column":1}},"children":[{"type":"text","value":"secure tokens","position":{"start":{"line":182,"column":1},"end":{"line":182,"column":1}},"key":"vjMaqhd5D6"}],"key":"n4UGJ43Yz7"},{"type":"text","value":" to enable ","position":{"start":{"line":182,"column":1},"end":{"line":182,"column":1}},"key":"Bi4SeMVB3i"},{"type":"emphasis","position":{"start":{"line":182,"column":1},"end":{"line":182,"column":1}},"children":[{"type":"text","value":"write","position":{"start":{"line":182,"column":1},"end":{"line":182,"column":1}},"key":"kNM4ZMS3px"}],"key":"g3XV2lRJwr"},{"type":"text","value":" (and sometimes ","position":{"start":{"line":182,"column":1},"end":{"line":182,"column":1}},"key":"uBUtwJJrdA"},{"type":"emphasis","position":{"start":{"line":182,"column":1},"end":{"line":182,"column":1}},"children":[{"type":"text","value":"read","position":{"start":{"line":182,"column":1},"end":{"line":182,"column":1}},"key":"xx0lZPohzX"}],"key":"jayHLhd9q9"},{"type":"text","value":") ","position":{"start":{"line":182,"column":1},"end":{"line":182,"column":1}},"key":"T6DMsshk44"},{"type":"emphasis","position":{"start":{"line":182,"column":1},"end":{"line":182,"column":1}},"children":[{"type":"text","value":"access","position":{"start":{"line":182,"column":1},"end":{"line":182,"column":1}},"key":"gxxd1jqTCO"}],"key":"XOCaModIPf"},{"type":"text","value":" to GitHub repositories.","position":{"start":{"line":182,"column":1},"end":{"line":182,"column":1}},"key":"jGVQkS57bB"}],"key":"rc1ah7vCDn"},{"type":"listItem","spread":true,"position":{"start":{"line":183,"column":1},"end":{"line":184,"column":1}},"children":[{"type":"text","value":"You can opt-in to notifications on a repo. The default, which can be easily changed, is to receive email.","position":{"start":{"line":183,"column":1},"end":{"line":183,"column":1}},"key":"pNrdJ7gAg5"}],"key":"R482cCGUAk"}],"key":"p6Nj0ItAro"},{"type":"heading","depth":3,"position":{"start":{"line":185,"column":1},"end":{"line":185,"column":1}},"children":[{"type":"text","value":"What’s Next?","position":{"start":{"line":185,"column":1},"end":{"line":185,"column":1}},"key":"j7yuIljyi9"}],"identifier":"whats-next","label":"What’s Next?","html_id":"whats-next","implicit":true,"key":"xGUHw335oN"},{"type":"paragraph","position":{"start":{"line":187,"column":1},"end":{"line":187,"column":1}},"children":[{"type":"text","value":"In the next section, we will learn the basics of version control using command-line ","position":{"start":{"line":187,"column":1},"end":{"line":187,"column":1}},"key":"WzKDdpg3Lr"},{"type":"inlineCode","value":"git","position":{"start":{"line":187,"column":1},"end":{"line":187,"column":1}},"key":"uIvdwdAWmL"},{"type":"text","value":".","position":{"start":{"line":187,"column":1},"end":{"line":187,"column":1}},"key":"iUonnsU1g8"}],"key":"QmUNDuB2wY"},{"type":"heading","depth":2,"position":{"start":{"line":189,"column":1},"end":{"line":189,"column":1}},"children":[{"type":"text","value":"References","position":{"start":{"line":189,"column":1},"end":{"line":189,"column":1}},"key":"lHqg3p3R7Q"}],"identifier":"references","label":"References","html_id":"references","implicit":true,"key":"ZhcHOPTF5q"},{"type":"list","ordered":true,"start":1,"spread":false,"position":{"start":{"line":191,"column":1},"end":{"line":193,"column":1}},"children":[{"type":"listItem","spread":true,"position":{"start":{"line":191,"column":1},"end":{"line":191,"column":1}},"children":[{"type":"link","url":"https://docs.github.com/en/authentication/keeping-your-account-and-data-secure/creating-a-personal-access-token","position":{"start":{"line":191,"column":1},"end":{"line":191,"column":1}},"children":[{"type":"text","value":"GitHub Personal Access Token (https)","position":{"start":{"line":191,"column":1},"end":{"line":191,"column":1}},"key":"y6DMxUjktz"}],"urlSource":"https://docs.github.com/en/authentication/keeping-your-account-and-data-secure/creating-a-personal-access-token","key":"D60Yu3mzed"}],"key":"NMpx9G3HWz"},{"type":"listItem","spread":true,"position":{"start":{"line":192,"column":1},"end":{"line":192,"column":1}},"children":[{"type":"link","url":"https://docs.github.com/en/github/authenticating-to-github/connecting-to-github-with-ssh","position":{"start":{"line":192,"column":1},"end":{"line":192,"column":1}},"children":[{"type":"text","value":"GitHub Public/Private Keypair (ssh)","position":{"start":{"line":192,"column":1},"end":{"line":192,"column":1}},"key":"TkFFhi4OST"}],"urlSource":"https://docs.github.com/en/github/authenticating-to-github/connecting-to-github-with-ssh","key":"iBpGMvOjtl"}],"key":"KcHPRgKQe8"},{"type":"listItem","spread":true,"position":{"start":{"line":193,"column":1},"end":{"line":193,"column":1}},"children":[{"type":"link","url":"https://swcarpentry.github.io/git-novice/07-github.html","position":{"start":{"line":193,"column":1},"end":{"line":193,"column":1}},"children":[{"type":"text","value":"Remotes in GitHub (Carpentries Tutorial)","position":{"start":{"line":193,"column":1},"end":{"line":193,"column":1}},"key":"ty09AcQREC"}],"urlSource":"https://swcarpentry.github.io/git-novice/07-github.html","key":"HTmAWY2FM7"}],"key":"NSB6RhJ7ha"}],"key":"VxSzNEA3lB"}],"key":"eiyXNDgEO9"}],"key":"FhGRYFuUdT"},"references":{"cite":{"order":[],"data":{}}},"footer":{"navigation":{"prev":{"title":"Cloning and Forking a Repository","url":"/github-cloning-forking","group":"Foundational skills"},"next":{"title":"Basic Version Control with git","url":"/basic-git","group":"Foundational skills"}}},"domain":"http://localhost:3000"}