{"version":2,"kind":"Notebook","sha256":"b3cc67e497ca26b4246cb5f68102ddf62e1ab31c48d60bc909b94e560f1d15ff","slug":"jupyterlab","location":"/foundations/jupyterlab.ipynb","dependencies":[],"frontmatter":{"title":"JupyterLab","content_includes_title":false,"kernelspec":{"name":"python3","display_name":"Python 3 (ipykernel)","language":"python"},"authors":[{"id":"Project Pythia Community","name":"Project Pythia Community"}],"open_access":true,"license":{"content":{"id":"Apache-2.0","url":"https://opensource.org/licenses/Apache-2.0","name":"Apache License 2.0","free":true,"osi":true},"code":{"id":"CC-BY-4.0","url":"https://creativecommons.org/licenses/by/4.0/","name":"Creative Commons Attribution 4.0 International","free":true,"CC":true}},"github":"https://github.com/projectpythia-mystmd/pythia-foundations","copyright":"2024","abbreviations":{"FOSS":"Free and open-source software","VCS":"Version control system","FTP":"File transfer protocol","TCP":"Transmission Control Protocol"},"numbering":{"title":{"offset":2}},"edit_url":"https://github.com/projectpythia-mystmd/pythia-foundations/blob/main/foundations/jupyterlab.ipynb","thumbnail":"/pythia-foundations/build/binder-highlight-dfda0b40ae0fdda40225145a419ca859.png","exports":[{"format":"ipynb","filename":"jupyterlab.ipynb","url":"/pythia-foundations/build/jupyterlab-d2d16a5e7d7fef2204d8aa8dff1306ea.ipynb"}]},"widgets":{},"mdast":{"type":"root","children":[{"type":"block","kind":"notebook-content","data":{"id":"3rIfwtTKpQLf"},"children":[{"type":"thematicBreak","position":{"start":{"line":1,"column":1},"end":{"line":1,"column":1}},"key":"GaFr0G8wwF"}],"identifier":"3rifwttkpqlf","label":"3rIfwtTKpQLf","html_id":"id-3rifwttkpqlf","key":"t0ig9o4e5u"},{"type":"block","kind":"notebook-content","data":{"id":"MkdbWkKzfegV","jp-MarkdownHeadingCollapsed":true,"tags":[]},"children":[{"type":"heading","depth":2,"position":{"start":{"line":1,"column":1},"end":{"line":1,"column":1}},"children":[{"type":"text","value":"Overview","position":{"start":{"line":1,"column":1},"end":{"line":1,"column":1}},"key":"SbL5VC8HNi"}],"identifier":"overview","label":"Overview","html_id":"overview","implicit":true,"key":"v2JfapO3US"},{"type":"paragraph","position":{"start":{"line":3,"column":1},"end":{"line":3,"column":1}},"children":[{"type":"text","value":"JupyterLab is a popular web application on which users can create and write their Jupyter Notebooks, as well as explore data, install software, etc. This section will introduce the JupyterLab interface and cover details of JupyterLab Notebooks.","position":{"start":{"line":3,"column":1},"end":{"line":3,"column":1}},"key":"k0YLe1htfT"}],"key":"S0XAQU98jp"},{"type":"list","ordered":true,"start":1,"spread":false,"position":{"start":{"line":5,"column":1},"end":{"line":7,"column":1}},"children":[{"type":"listItem","spread":true,"position":{"start":{"line":5,"column":1},"end":{"line":5,"column":1}},"children":[{"type":"text","value":"Set Up","position":{"start":{"line":5,"column":1},"end":{"line":5,"column":1}},"key":"BqYHhAPdSJ"}],"key":"h9JWbOhGhr"},{"type":"listItem","spread":true,"position":{"start":{"line":6,"column":1},"end":{"line":6,"column":1}},"children":[{"type":"text","value":"The JupyterLab Interface","position":{"start":{"line":6,"column":1},"end":{"line":6,"column":1}},"key":"JBaGONBa8Z"}],"key":"Wzfq9ljRBz"},{"type":"listItem","spread":true,"position":{"start":{"line":7,"column":1},"end":{"line":7,"column":1}},"children":[{"type":"text","value":"Running JupyterLab Notebooks","position":{"start":{"line":7,"column":1},"end":{"line":7,"column":1}},"key":"t9ykkc2Rlk"}],"key":"JZvNksmEgr"}],"key":"adwlEGWk9t"}],"identifier":"mkdbwkkzfegv","label":"MkdbWkKzfegV","html_id":"mkdbwkkzfegv","visibility":"show","key":"ahvHWIAdhn"},{"type":"block","kind":"notebook-content","data":{"id":"yt-WtTrcpRpo"},"children":[{"type":"heading","depth":2,"position":{"start":{"line":1,"column":1},"end":{"line":1,"column":1}},"children":[{"type":"text","value":"Prerequisites","position":{"start":{"line":1,"column":1},"end":{"line":1,"column":1}},"key":"ITqR7NU5pU"}],"identifier":"prerequisites","label":"Prerequisites","html_id":"prerequisites","implicit":true,"key":"viOdpLoDfU"},{"type":"table","position":{"start":{"line":2,"column":1},"end":{"line":5,"column":1}},"children":[{"type":"tableRow","position":{"start":{"line":2,"column":1},"end":{"line":2,"column":1}},"children":[{"type":"tableCell","header":true,"position":{"start":{"line":2,"column":1},"end":{"line":2,"column":1}},"children":[{"type":"text","value":"Concepts","position":{"start":{"line":2,"column":1},"end":{"line":2,"column":1}},"key":"HyZeMVMuKv"}],"key":"OrfMVHThqN"},{"type":"tableCell","header":true,"position":{"start":{"line":2,"column":1},"end":{"line":2,"column":1}},"children":[{"type":"text","value":"Importance","position":{"start":{"line":2,"column":1},"end":{"line":2,"column":1}},"key":"swJnw8IeTC"}],"key":"bPiy0noL4F"},{"type":"tableCell","header":true,"position":{"start":{"line":2,"column":1},"end":{"line":2,"column":1}},"children":[{"type":"text","value":"Notes","position":{"start":{"line":2,"column":1},"end":{"line":2,"column":1}},"key":"urhrwRA5V3"}],"key":"bGrskuMVVP"}],"key":"j6gGwvf40Z"},{"type":"tableRow","position":{"start":{"line":4,"column":1},"end":{"line":4,"column":1}},"children":[{"type":"tableCell","position":{"start":{"line":4,"column":1},"end":{"line":4,"column":1}},"children":[{"type":"link","url":"/getting-started-jupyter","position":{"start":{"line":4,"column":1},"end":{"line":4,"column":1}},"children":[{"type":"text","value":"Getting Started with Jupyter","position":{"start":{"line":4,"column":1},"end":{"line":4,"column":1}},"key":"vSStkSeDJz"}],"urlSource":"getting-started-jupyter","dataUrl":"/getting-started-jupyter.json","internal":true,"protocol":"file","key":"r5Q6eug0wC"}],"key":"xGrFrKU4e6"},{"type":"tableCell","position":{"start":{"line":4,"column":1},"end":{"line":4,"column":1}},"children":[{"type":"text","value":"Helpful","position":{"start":{"line":4,"column":1},"end":{"line":4,"column":1}},"key":"PuEC1ZKKaS"}],"key":"PzCFrxVNhj"},{"type":"tableCell","position":{"start":{"line":4,"column":1},"end":{"line":4,"column":1}},"children":[],"key":"nUUtowcv0X"}],"key":"MwpiSm6Kik"},{"type":"tableRow","position":{"start":{"line":5,"column":1},"end":{"line":5,"column":1}},"children":[{"type":"tableCell","position":{"start":{"line":5,"column":1},"end":{"line":5,"column":1}},"children":[{"type":"link","url":"https://foundations.projectpythia.org/foundations/jupyter.html","position":{"start":{"line":5,"column":1},"end":{"line":5,"column":1}},"children":[{"type":"text","value":"Installing and Running Python: Python in Jupyter","position":{"start":{"line":5,"column":1},"end":{"line":5,"column":1}},"key":"Z4hVj4M5Rn"}],"urlSource":"https://foundations.projectpythia.org/foundations/jupyter.html","key":"sutO4MXlEp"}],"key":"kYr70gjptS"},{"type":"tableCell","position":{"start":{"line":5,"column":1},"end":{"line":5,"column":1}},"children":[{"type":"text","value":"Helpful","position":{"start":{"line":5,"column":1},"end":{"line":5,"column":1}},"key":"WauRHr4lg4"}],"key":"kTtobSFeZJ"},{"type":"tableCell","position":{"start":{"line":5,"column":1},"end":{"line":5,"column":1}},"children":[],"key":"RkxeDdqRMu"}],"key":"HDax46t2rf"}],"key":"WsXK9Tyhig"},{"type":"list","ordered":false,"spread":false,"position":{"start":{"line":7,"column":1},"end":{"line":7,"column":1}},"children":[{"type":"listItem","spread":true,"position":{"start":{"line":7,"column":1},"end":{"line":7,"column":1}},"children":[{"type":"strong","position":{"start":{"line":7,"column":1},"end":{"line":7,"column":1}},"children":[{"type":"text","value":"Time to learn","position":{"start":{"line":7,"column":1},"end":{"line":7,"column":1}},"key":"gvw4LnE0my"}],"key":"O6ebpbCwVW"},{"type":"text","value":": 50 minutes","position":{"start":{"line":7,"column":1},"end":{"line":7,"column":1}},"key":"Z2m10KCKxy"}],"key":"Slm06TFdLG"}],"key":"XbExQBOJa9"}],"identifier":"yt-wttrcprpo","label":"yt-WtTrcpRpo","html_id":"yt-wttrcprpo","key":"lP98fiNhET"},{"type":"block","kind":"notebook-content","data":{"id":"nvLyiIa8pTI5"},"children":[{"type":"thematicBreak","position":{"start":{"line":1,"column":1},"end":{"line":1,"column":1}},"key":"mGvuFJVoF3"}],"identifier":"nvlyiia8pti5","label":"nvLyiIa8pTI5","html_id":"nvlyiia8pti5","key":"SGunwg29rX"},{"type":"block","kind":"notebook-content","data":{"id":"eRjK14BjeQXA","tags":[]},"children":[{"type":"heading","depth":2,"position":{"start":{"line":1,"column":1},"end":{"line":1,"column":1}},"children":[{"type":"text","value":"Set Up","position":{"start":{"line":1,"column":1},"end":{"line":1,"column":1}},"key":"tG8fSvLRFW"}],"identifier":"set-up","label":"Set Up","html_id":"set-up","implicit":true,"key":"GFzMVdl30g"},{"type":"paragraph","position":{"start":{"line":3,"column":1},"end":{"line":3,"column":1}},"children":[{"type":"text","value":"To launch the JupyterLab interface in your browser, follow the instructions in ","position":{"start":{"line":3,"column":1},"end":{"line":3,"column":1}},"key":"aEpRiGKUs9"},{"type":"link","url":"https://foundations.projectpythia.org/foundations/jupyter.html","position":{"start":{"line":3,"column":1},"end":{"line":3,"column":1}},"children":[{"type":"text","value":"Installing and Running Python: Python in Jupyter","position":{"start":{"line":3,"column":1},"end":{"line":3,"column":1}},"key":"CXkX25cYMl"}],"urlSource":"https://foundations.projectpythia.org/foundations/jupyter.html","key":"po9jPUo2IU"},{"type":"text","value":".","position":{"start":{"line":3,"column":1},"end":{"line":3,"column":1}},"key":"v0jUXAJN2S"}],"key":"LxFbhyK5Gu"},{"type":"paragraph","position":{"start":{"line":5,"column":1},"end":{"line":5,"column":1}},"children":[{"type":"text","value":"If, instead, you want to follow along using a provided remote JupyterLab instance, launch this notebook via ","position":{"start":{"line":5,"column":1},"end":{"line":5,"column":1}},"key":"vzDkHVhEc7"},{"type":"link","url":"https://mybinder.org/","position":{"start":{"line":5,"column":1},"end":{"line":5,"column":1}},"children":[{"type":"text","value":"Binder","position":{"start":{"line":5,"column":1},"end":{"line":5,"column":1}},"key":"DKB8eWhXa0"}],"urlSource":"https://mybinder.org/","key":"yn5UUe2JW2"},{"type":"text","value":" using the launch icon at the top of this page,","position":{"start":{"line":5,"column":1},"end":{"line":5,"column":1}},"key":"HRvMubTgMo"}],"key":"nw8n3SLrDS"},{"type":"image","url":"/pythia-foundations/build/binder-highlight-dfda0b40ae0fdda40225145a419ca859.png","alt":"Binder Launch","title":"Binder launch button location","position":{"start":{"line":7,"column":1},"end":{"line":7,"column":1}},"key":"QUogNKto8C","urlSource":"../images/binder-highlight.png"},{"type":"paragraph","position":{"start":{"line":9,"column":1},"end":{"line":9,"column":1}},"children":[{"type":"text","value":"and follow along from there! If launching Binder, take note of the ","position":{"start":{"line":9,"column":1},"end":{"line":9,"column":1}},"key":"uT4MgsfUR2"},{"type":"inlineCode","value":"Launcher","position":{"start":{"line":9,"column":1},"end":{"line":9,"column":1}},"key":"az58lBwRXx"},{"type":"text","value":" tab in the upper-left (see interface below). Click there to find yourself in the same interface moving forward, and feel free to refer back to this tab to follow along.","position":{"start":{"line":9,"column":1},"end":{"line":9,"column":1}},"key":"ycAZbxgaYB"}],"key":"VlpBVzVsFA"}],"identifier":"erjk14bjeqxa","label":"eRjK14BjeQXA","html_id":"erjk14bjeqxa","visibility":"show","key":"zjPEu2hGtw"},{"type":"block","kind":"notebook-content","data":{"id":"Qe2fbSa2gS2X"},"children":[{"type":"heading","depth":2,"position":{"start":{"line":1,"column":1},"end":{"line":1,"column":1}},"children":[{"type":"text","value":"The JupyterLab Interface","position":{"start":{"line":1,"column":1},"end":{"line":1,"column":1}},"key":"YkCQFFFlQi"}],"identifier":"the-jupyterlab-interface","label":"The JupyterLab Interface","html_id":"the-jupyterlab-interface","implicit":true,"key":"uIt9WR6tQM"},{"type":"paragraph","position":{"start":{"line":3,"column":1},"end":{"line":3,"column":1}},"children":[{"type":"text","value":"Go to your browser and take a look at the JupyterLab interface.","position":{"start":{"line":3,"column":1},"end":{"line":3,"column":1}},"key":"FZo141XUyM"}],"key":"elE5JS9NYT"},{"type":"paragraph","position":{"start":{"line":5,"column":1},"end":{"line":5,"column":1}},"children":[{"type":"text","value":"With a base installation of JupyterLab your screen should look similar to the image below.","position":{"start":{"line":5,"column":1},"end":{"line":5,"column":1}},"key":"T5GFp0D80w"}],"key":"sNCeq9jqu0"},{"type":"paragraph","position":{"start":{"line":7,"column":1},"end":{"line":7,"column":1}},"children":[{"type":"text","value":"Notice:","position":{"start":{"line":7,"column":1},"end":{"line":7,"column":1}},"key":"euTauhnqb9"}],"key":"shrFk8e17g"},{"type":"list","ordered":false,"spread":false,"position":{"start":{"line":8,"column":1},"end":{"line":13,"column":1}},"children":[{"type":"listItem","spread":true,"position":{"start":{"line":8,"column":1},"end":{"line":8,"column":1}},"children":[{"type":"text","value":"The ","position":{"start":{"line":8,"column":1},"end":{"line":8,"column":1}},"key":"Pe0CChTSrP"},{"type":"strong","position":{"start":{"line":8,"column":1},"end":{"line":8,"column":1}},"children":[{"type":"text","value":"Menu Bar","position":{"start":{"line":8,"column":1},"end":{"line":8,"column":1}},"key":"RPxOAz7Byw"}],"key":"IrzWY1dc13"},{"type":"text","value":" at the top of the screen, containing the typical dropdown menus: “File”, “Edit”, “View”, etc.","position":{"start":{"line":8,"column":1},"end":{"line":8,"column":1}},"key":"Cdl0EAFDgc"}],"key":"OQivfgmxek"},{"type":"listItem","spread":true,"position":{"start":{"line":9,"column":1},"end":{"line":9,"column":1}},"children":[{"type":"text","value":"Below that is the ","position":{"start":{"line":9,"column":1},"end":{"line":9,"column":1}},"key":"dfQTnnLmfm"},{"type":"strong","position":{"start":{"line":9,"column":1},"end":{"line":9,"column":1}},"children":[{"type":"text","value":"Workspace Area","position":{"start":{"line":9,"column":1},"end":{"line":9,"column":1}},"key":"wx0GawyaDV"}],"key":"XhjSDgfaXd"},{"type":"text","value":" (currently contains the Launcher).","position":{"start":{"line":9,"column":1},"end":{"line":9,"column":1}},"key":"O5eOF1ApuQ"}],"key":"CHtLalNv6T"},{"type":"listItem","spread":true,"position":{"start":{"line":10,"column":1},"end":{"line":10,"column":1}},"children":[{"type":"text","value":"The ","position":{"start":{"line":10,"column":1},"end":{"line":10,"column":1}},"key":"FACjs7PJuA"},{"type":"strong","position":{"start":{"line":10,"column":1},"end":{"line":10,"column":1}},"children":[{"type":"text","value":"Launcher","position":{"start":{"line":10,"column":1},"end":{"line":10,"column":1}},"key":"Vv0Qgqx3eX"}],"key":"FW3rn3BJZG"},{"type":"text","value":" is a quick shortcut for accessing the Console/Terminal, for creating new Notebooks, or for creating new Text or Markdown files.","position":{"start":{"line":10,"column":1},"end":{"line":10,"column":1}},"key":"LAPz1TeUzl"}],"key":"tfx4I4gzW8"},{"type":"listItem","spread":true,"position":{"start":{"line":11,"column":1},"end":{"line":11,"column":1}},"children":[{"type":"text","value":"On the left is a ","position":{"start":{"line":11,"column":1},"end":{"line":11,"column":1}},"key":"BQS3zdLB59"},{"type":"strong","position":{"start":{"line":11,"column":1},"end":{"line":11,"column":1}},"children":[{"type":"text","value":"Collapsible Sidebar","position":{"start":{"line":11,"column":1},"end":{"line":11,"column":1}},"key":"vcWNwR8X8F"}],"key":"C95UAWZMkf"},{"type":"text","value":". It currently contains the File Browser, but you can also select the Running Tabs and Kernels, the Table of Contents, and the Extensions Manager.","position":{"start":{"line":11,"column":1},"end":{"line":11,"column":1}},"key":"VVV7qXCkDt"}],"key":"KLI9rLfFVP"},{"type":"listItem","spread":true,"position":{"start":{"line":12,"column":1},"end":{"line":13,"column":1}},"children":[{"type":"text","value":"Below everything is the ","position":{"start":{"line":12,"column":1},"end":{"line":12,"column":1}},"key":"RA4BsU30XS"},{"type":"strong","position":{"start":{"line":12,"column":1},"end":{"line":12,"column":1}},"children":[{"type":"text","value":"Information Bar","position":{"start":{"line":12,"column":1},"end":{"line":12,"column":1}},"key":"ENB2uwN2xN"}],"key":"JX4dHvzKlR"},{"type":"text","value":", which is context sensitive. We will touch on this more.","position":{"start":{"line":12,"column":1},"end":{"line":12,"column":1}},"key":"EE3ZxncEdi"}],"key":"iBBcD6fohA"}],"key":"lergfE2wlU"},{"type":"image","url":"/pythia-foundations/build/interface_labeled-0e44ba0d4be7a90ea74ab6de4ee9bc48.png","alt":"Interface","position":{"start":{"line":14,"column":1},"end":{"line":14,"column":1}},"key":"kFlzm8CbAC","urlSource":"../images/interface_labeled.png"},{"type":"paragraph","position":{"start":{"line":16,"column":1},"end":{"line":16,"column":1}},"children":[{"type":"text","value":"We will now take a closer look at certain aspects and features of the JupyterLab Interface.","position":{"start":{"line":16,"column":1},"end":{"line":16,"column":1}},"key":"NFohEiuiTt"}],"key":"tcRL05zmKW"}],"identifier":"qe2fbsa2gs2x","label":"Qe2fbSa2gS2X","html_id":"qe2fbsa2gs2x","key":"wE4kDlmu7E"},{"type":"block","kind":"notebook-content","data":{"id":"zpDZFM3ngsY6"},"children":[{"type":"heading","depth":3,"position":{"start":{"line":1,"column":1},"end":{"line":1,"column":1}},"children":[{"type":"text","value":"Left Sidebar","position":{"start":{"line":1,"column":1},"end":{"line":1,"column":1}},"key":"QIqPuM6n21"}],"identifier":"left-sidebar","label":"Left Sidebar","html_id":"left-sidebar","implicit":true,"key":"oqFZc6nfCz"},{"type":"paragraph","position":{"start":{"line":3,"column":1},"end":{"line":3,"column":1}},"children":[{"type":"text","value":"The Collapsible Left Sidebar is open to the ","position":{"start":{"line":3,"column":1},"end":{"line":3,"column":1}},"key":"e9FZr54q9H"},{"type":"strong","position":{"start":{"line":3,"column":1},"end":{"line":3,"column":1}},"children":[{"type":"text","value":"File Browser Tab","position":{"start":{"line":3,"column":1},"end":{"line":3,"column":1}},"key":"h9Xw30RNL0"}],"key":"Ri9WyxAteV"},{"type":"text","value":" at launch. Clicking the File Browser Tab will collapse the sidebar or reopen it to this tab.","position":{"start":{"line":3,"column":1},"end":{"line":3,"column":1}},"key":"VRSSAHrUiy"}],"key":"fyCmNk6b0u"},{"type":"list","ordered":false,"spread":false,"position":{"start":{"line":4,"column":1},"end":{"line":8,"column":1}},"children":[{"type":"listItem","spread":true,"position":{"start":{"line":4,"column":1},"end":{"line":4,"column":1}},"children":[{"type":"text","value":"Within this tab, you will see the “+” button, which allows you to create a new launcher.","position":{"start":{"line":4,"column":1},"end":{"line":4,"column":1}},"key":"A9PPtaqDZU"}],"key":"mL2elyKshj"},{"type":"listItem","spread":true,"position":{"start":{"line":5,"column":1},"end":{"line":5,"column":1}},"children":[{"type":"text","value":"Next to that is the “+ folder” button which allows you to create a new folder that then appears below “Name” in the contents of your directory. Double click the folder to enter it, right click the folder for options, or press the “root folder” icon to return to the root directory. The root directory is the directory from which JupyterLab was launched. You cannot go above the root directory.","position":{"start":{"line":5,"column":1},"end":{"line":5,"column":1}},"key":"fjF6d38scb"}],"key":"hezmyp7RcR"},{"type":"listItem","spread":true,"position":{"start":{"line":6,"column":1},"end":{"line":6,"column":1}},"children":[{"type":"text","value":"The “upload” button (looks like an arrow pointing up) allows you to upload files to the current folder.","position":{"start":{"line":6,"column":1},"end":{"line":6,"column":1}},"key":"kB0zaHIQsA"}],"key":"rvujO1m8ix"},{"type":"listItem","spread":true,"position":{"start":{"line":7,"column":1},"end":{"line":8,"column":1}},"children":[{"type":"text","value":"The “refresh” button refreshes the File Browser.","position":{"start":{"line":7,"column":1},"end":{"line":7,"column":1}},"key":"WHBg86kEiG"}],"key":"BH1gqd6U4H"}],"key":"sZVgsyb2HF"},{"type":"paragraph","position":{"start":{"line":9,"column":1},"end":{"line":9,"column":1}},"children":[{"type":"text","value":"Below the File Browser Tab is the ","position":{"start":{"line":9,"column":1},"end":{"line":9,"column":1}},"key":"Xifr6RipSp"},{"type":"strong","position":{"start":{"line":9,"column":1},"end":{"line":9,"column":1}},"children":[{"type":"text","value":"Running Tabs and Kernels Tab","position":{"start":{"line":9,"column":1},"end":{"line":9,"column":1}},"key":"f0BPvnhwHF"}],"key":"nIj137y7y6"},{"type":"text","value":". Currently, this tab doesn’t have much in it. We will revisit this when we have running kernels. Remember that Kernels are background processes, so closing a tab (Terminal or Notebook) doesn’t shut down the kernel. You have to do that manually.","position":{"start":{"line":9,"column":1},"end":{"line":9,"column":1}},"key":"qDCMlOaeuC"}],"key":"p9N4vSliao"},{"type":"image","url":"/pythia-foundations/build/running-tabs-kernels-ec105323d7da7140ef7d15e3c7e60018.png","key":"UdLAS7Aqt7","urlSource":"../images/running-tabs-kernels.png"},{"type":"paragraph","position":{"start":{"line":14,"column":1},"end":{"line":14,"column":1}},"children":[{"type":"text","value":"The ","position":{"start":{"line":14,"column":1},"end":{"line":14,"column":1}},"key":"hQeN4jfral"},{"type":"strong","position":{"start":{"line":14,"column":1},"end":{"line":14,"column":1}},"children":[{"type":"text","value":"Table of Contents Tab","position":{"start":{"line":14,"column":1},"end":{"line":14,"column":1}},"key":"EamU9Flsi2"}],"key":"bTCOPfuTC0"},{"type":"text","value":" is auto-populated based on the headings and subheadings used in the Markdown cells of your notebook. It allows you to quickly jump between sections of the document.","position":{"start":{"line":14,"column":1},"end":{"line":14,"column":1}},"key":"xu9hpD0akD"}],"key":"CFQa2tQQXx"},{"type":"image","url":"/pythia-foundations/build/table-contents-f7baf935a223a29cee1cd7690416e1b8.png","key":"WEAGbw2Jaa","urlSource":"../images/table-contents.png"},{"type":"paragraph","position":{"start":{"line":18,"column":1},"end":{"line":18,"column":1}},"children":[{"type":"text","value":"Last is the ","position":{"start":{"line":18,"column":1},"end":{"line":18,"column":1}},"key":"xvDWdfnSR1"},{"type":"strong","position":{"start":{"line":18,"column":1},"end":{"line":18,"column":1}},"children":[{"type":"text","value":"Extensions Manager Tab","position":{"start":{"line":18,"column":1},"end":{"line":18,"column":1}},"key":"PZ0uK6sBLx"}],"key":"P53Rzer1nb"},{"type":"text","value":" where you can customize or enhance any part of JupyterLab. These customizations could pertain to themes or keyboard shortcuts, for example. We will not be covering JupyterLab extensions, but you can read more about them ","position":{"start":{"line":18,"column":1},"end":{"line":18,"column":1}},"key":"TcPjsk30wJ"},{"type":"link","url":"https://jupyterlab.readthedocs.io/en/stable/user/extensions.html","position":{"start":{"line":18,"column":1},"end":{"line":18,"column":1}},"children":[{"type":"text","value":"here","position":{"start":{"line":18,"column":1},"end":{"line":18,"column":1}},"key":"DZih2RTYmX"}],"urlSource":"https://jupyterlab.readthedocs.io/en/stable/user/extensions.html","key":"qvfAxnq86X"},{"type":"text","value":".","position":{"start":{"line":18,"column":1},"end":{"line":18,"column":1}},"key":"UqaE3dRg5J"}],"key":"UVujmduiLb"},{"type":"image","url":"/pythia-foundations/build/extensions-243105e8e7a183b1dd65e50235388263.png","key":"CwAe9jZuF4","urlSource":"../images/extensions.png"}],"identifier":"zpdzfm3ngsy6","label":"zpDZFM3ngsY6","html_id":"zpdzfm3ngsy6","key":"XX3qrZFmo1"},{"type":"block","kind":"notebook-content","data":{"id":"1WPljwIRg1KH"},"children":[{"type":"heading","depth":3,"position":{"start":{"line":1,"column":1},"end":{"line":1,"column":1}},"children":[{"type":"text","value":"Terminals","position":{"start":{"line":1,"column":1},"end":{"line":1,"column":1}},"key":"r7nfcK4zrn"}],"identifier":"terminals","label":"Terminals","html_id":"terminals","implicit":true,"key":"EL0uEdMtAU"},{"type":"paragraph","position":{"start":{"line":3,"column":1},"end":{"line":3,"column":1}},"children":[{"type":"text","value":"Let’s select the Running Tabs and Kernels Tab in the Left Sidebar and see how it changes when we’ve used the Launcher.","position":{"start":{"line":3,"column":1},"end":{"line":3,"column":1}},"key":"tsMyHWFtak"}],"key":"zQGWnvgK2U"},{"type":"paragraph","position":{"start":{"line":5,"column":1},"end":{"line":5,"column":1}},"children":[{"type":"text","value":"Open a Terminal in the Launcher. It should look very similar to the desktop terminal that you initially launched JupyterLab from, but is running from within JupyterLab, within your existing Conda environment, and within the directory you launched JupyterLab from (the same root folder shown in the File Browser Tab). Notice that there is now a Terminal listed in the Running Terminals Tab.","position":{"start":{"line":5,"column":1},"end":{"line":5,"column":1}},"key":"LBb9KEvWeY"}],"key":"qizCSjaUAG"},{"type":"paragraph","position":{"start":{"line":7,"column":1},"end":{"line":7,"column":1}},"children":[{"type":"text","value":"In the terminal you can use your usual terminal commands. For example, in the terminal window, run:","position":{"start":{"line":7,"column":1},"end":{"line":7,"column":1}},"key":"nbr2quxCEe"}],"key":"RXx95TKjLY"},{"type":"code","lang":"","value":"$ mkdir test","position":{"start":{"line":9,"column":1},"end":{"line":11,"column":1}},"identifier":"1wpljwirg1kh-code-0","enumerator":"1","html_id":"id-1wpljwirg1kh-code-0","key":"Cwtt47SNOB"},{"type":"paragraph","position":{"start":{"line":13,"column":1},"end":{"line":13,"column":1}},"children":[{"type":"text","value":"Select the File Browser Tab, refresh it, and see that your new folder is there.","position":{"start":{"line":13,"column":1},"end":{"line":13,"column":1}},"key":"EmxfZJVcBl"}],"key":"BIwAdkPSZu"},{"type":"paragraph","position":{"start":{"line":15,"column":1},"end":{"line":15,"column":1}},"children":[{"type":"text","value":"In the Terminal Window run:","position":{"start":{"line":15,"column":1},"end":{"line":15,"column":1}},"key":"bqb2569nIb"}],"key":"VGr0yq2uuD"},{"type":"code","lang":"","value":"$ rmdir test","position":{"start":{"line":17,"column":1},"end":{"line":19,"column":1}},"identifier":"1wpljwirg1kh-code-1","enumerator":"2","html_id":"id-1wpljwirg1kh-code-1","key":"XzUrFHA2r3"},{"type":"paragraph","position":{"start":{"line":20,"column":1},"end":{"line":20,"column":1}},"children":[{"type":"text","value":"Hit refresh in the File Browser again to see that the directory is gone.","position":{"start":{"line":20,"column":1},"end":{"line":20,"column":1}},"key":"B0oKYL1FS5"}],"key":"aX50h6TQcG"},{"type":"image","url":"/pythia-foundations/build/terminal-306f0d22e6ad54ca8a09f2725580b997.png","alt":"Terminal","position":{"start":{"line":22,"column":1},"end":{"line":22,"column":1}},"key":"ZpT8q8PsJd","urlSource":"../images/terminal.png"},{"type":"paragraph","position":{"start":{"line":24,"column":1},"end":{"line":24,"column":1}},"children":[{"type":"text","value":"Back with the Running Terminals and Kernels Tab open, click the “X” in your workspace to close the Terminal window. Notice that the Terminal is still running in the background!  Click on the terminal in the Running Terminals and Kernels Tab to reopen it (and hit enter or return to get your prompt back). To truly close it, execute in the Terminal window:","position":{"start":{"line":24,"column":1},"end":{"line":24,"column":1}},"key":"N5wktWoP4A"}],"key":"VJN4dovMtt"},{"type":"code","lang":"","value":"$ exit","position":{"start":{"line":26,"column":1},"end":{"line":28,"column":1}},"identifier":"1wpljwirg1kh-code-2","enumerator":"3","html_id":"id-1wpljwirg1kh-code-2","key":"f8uiTAjFYi"},{"type":"paragraph","position":{"start":{"line":30,"column":1},"end":{"line":30,"column":1}},"children":[{"type":"text","value":"OR click the “X” shut down button in the Running Terminals tab.","position":{"start":{"line":30,"column":1},"end":{"line":30,"column":1}},"key":"J58l4V6oeD"}],"key":"HrR95IqgM3"},{"type":"paragraph","position":{"start":{"line":32,"column":1},"end":{"line":32,"column":1}},"children":[{"type":"text","value":"Doing so will return you to the Launcher.","position":{"start":{"line":32,"column":1},"end":{"line":32,"column":1}},"key":"pPK2zkQa6r"}],"key":"oR7U1G4ncx"},{"type":"div","class":"admonition alert alert-info","children":[{"type":"paragraph","children":[{"type":"text","value":"Info","key":"xkQ1MBVIZh"}],"key":"CYH1qEUYNN"},{"type":"text","value":"The terminal is running on the local host when JupyterLab is launched locally, and remote host when invoked through Jupyter Hub.","key":"DUQMsZZFqz"}],"key":"fn314eMPKs"}],"identifier":"1wpljwirg1kh","label":"1WPljwIRg1KH","html_id":"id-1wpljwirg1kh","key":"BQopHT3TJG"},{"type":"block","kind":"notebook-content","data":{"id":"iQAVvbtJg6pi"},"children":[{"type":"heading","depth":3,"position":{"start":{"line":1,"column":1},"end":{"line":1,"column":1}},"children":[{"type":"text","value":"Consoles","position":{"start":{"line":1,"column":1},"end":{"line":1,"column":1}},"key":"C9QafJTrjG"}],"identifier":"consoles","label":"Consoles","html_id":"consoles","implicit":true,"key":"Tz1Y73UL75"},{"type":"paragraph","position":{"start":{"line":3,"column":1},"end":{"line":3,"column":1}},"children":[{"type":"text","value":"Back in the Launcher, click the “Python 3” Console button. There is only one console option right now, but you could install more kernels into your Conda environment.","position":{"start":{"line":3,"column":1},"end":{"line":3,"column":1}},"key":"GGLQNTZsqA"}],"key":"HS5Smi8AZc"},{"type":"paragraph","position":{"start":{"line":5,"column":1},"end":{"line":5,"column":1}},"children":[{"type":"text","value":"There will be three dots while the kernel starts, then what loads looks like an IPython console. This is a place to execute Python commands in a stand alone workspace which is good for testing. Notice that the kernel started in the Running Terminals and Kernels tab!","position":{"start":{"line":5,"column":1},"end":{"line":5,"column":1}},"key":"GwQEGQ3cuC"}],"key":"PB5HHoZuIW"},{"type":"paragraph","position":{"start":{"line":7,"column":1},"end":{"line":7,"column":1}},"children":[{"type":"text","value":"Start in a “cell” at the bottom of the Console window. Type:","position":{"start":{"line":7,"column":1},"end":{"line":7,"column":1}},"key":"b66CUKcoXk"}],"key":"P6brUcqfNX"},{"type":"code","lang":"python","value":"i = 5\nprint(i)","position":{"start":{"line":8,"column":1},"end":{"line":11,"column":1}},"identifier":"iqavvbtjg6pi-code-0","enumerator":"4","html_id":"iqavvbtjg6pi-code-0","key":"HngQZKSnV0"},{"type":"paragraph","position":{"start":{"line":12,"column":1},"end":{"line":12,"column":1}},"children":[{"type":"text","value":"To execute the cell, type ","position":{"start":{"line":12,"column":1},"end":{"line":12,"column":1}},"key":"X6j26dqE4t"},{"type":"keyboard","children":[{"type":"text","value":"Shift","key":"cDvlmbfdDD"}],"key":"caTpYYwee0"},{"type":"text","value":"+","position":{"start":{"line":12,"column":1},"end":{"line":12,"column":1}},"key":"SolY2RzUlC"},{"type":"keyboard","children":[{"type":"text","value":"Enter","key":"pDH574PMka"}],"key":"BpH4Lwhz2I"},{"type":"text","value":". Notice that the console redisplays the code you wrote, labels it with a number, and displays (prints) the output to the screen.","position":{"start":{"line":12,"column":1},"end":{"line":12,"column":1}},"key":"mHn9uVULJ1"}],"key":"lsl7osWpsQ"},{"type":"paragraph","position":{"start":{"line":14,"column":1},"end":{"line":14,"column":1}},"children":[{"type":"text","value":"In the next cell, enter:","position":{"start":{"line":14,"column":1},"end":{"line":14,"column":1}},"key":"coov6Yhivt"}],"key":"fdfGuCydAK"},{"type":"code","lang":"python","value":"s = 'Hello, World!'\nprint(f's = {s}')\ns","position":{"start":{"line":15,"column":1},"end":{"line":19,"column":1}},"identifier":"iqavvbtjg6pi-code-1","enumerator":"5","html_id":"iqavvbtjg6pi-code-1","key":"AYoTuPC2Ix"},{"type":"paragraph","position":{"start":{"line":21,"column":1},"end":{"line":21,"column":1}},"children":[{"type":"text","value":"The first line of this code designates a string ","position":{"start":{"line":21,"column":1},"end":{"line":21,"column":1}},"key":"NMKe9YCtLs"},{"type":"inlineCode","value":"s","position":{"start":{"line":21,"column":1},"end":{"line":21,"column":1}},"key":"StRvzBu1OU"},{"type":"text","value":" with the value “Hello, World!”, the second line uses f-formatting to print the string, and the final line just calls up ","position":{"start":{"line":21,"column":1},"end":{"line":21,"column":1}},"key":"iCHZY1mDjH"},{"type":"inlineCode","value":"s","position":{"start":{"line":21,"column":1},"end":{"line":21,"column":1}},"key":"UVVykP9LNR"},{"type":"text","value":". The last line in the cell will always be returned (its value displayed) regardless of whether you called ","position":{"start":{"line":21,"column":1},"end":{"line":21,"column":1}},"key":"hsA1rBSXZB"},{"type":"inlineCode","value":"print","position":{"start":{"line":21,"column":1},"end":{"line":21,"column":1}},"key":"SPJw3IcJWL"},{"type":"text","value":". Type ","position":{"start":{"line":21,"column":1},"end":{"line":21,"column":1}},"key":"Oon3z9mngQ"},{"type":"keyboard","children":[{"type":"text","value":"Shift","key":"mwlQkrKMUn"}],"key":"Nef4mKCYcV"},{"type":"text","value":"+","position":{"start":{"line":21,"column":1},"end":{"line":21,"column":1}},"key":"OsAxTWgisu"},{"type":"keyboard","children":[{"type":"text","value":"Enter","key":"FiCHPu554Y"}],"key":"wlmwcRJ6wd"},{"type":"text","value":" to execute the cell. Again the output is labeled (this time with a 2), and we see the input code, the printed standard-out statement, and the return statement. The “return value” and the values “printed to screen” are different!","position":{"start":{"line":21,"column":1},"end":{"line":21,"column":1}},"key":"o1pOacNUSq"}],"key":"UFv2skpSfR"},{"type":"image","url":"/pythia-foundations/build/console-3a05ce0fbbdf42f766198414ced6712c.png","alt":"Console","position":{"start":{"line":23,"column":1},"end":{"line":23,"column":1}},"key":"HLiUXC1X9Q","urlSource":"../images/console.png"},{"type":"paragraph","position":{"start":{"line":25,"column":1},"end":{"line":25,"column":1}},"children":[{"type":"text","value":"Close the window and shut down the Console in the Running Kernels tab. We’re back to the Launcher again.","position":{"start":{"line":25,"column":1},"end":{"line":25,"column":1}},"key":"hYcZotSyoP"}],"key":"m6vBEWPPNB"}],"identifier":"iqavvbtjg6pi","label":"iQAVvbtJg6pi","html_id":"iqavvbtjg6pi","key":"q83iFaAXTg"},{"type":"block","kind":"notebook-content","data":{"id":"UDCCs37IhK7S"},"children":[{"type":"heading","depth":3,"position":{"start":{"line":1,"column":1},"end":{"line":1,"column":1}},"children":[{"type":"text","value":"Text Editor","position":{"start":{"line":1,"column":1},"end":{"line":1,"column":1}},"key":"DUXSAGEnyu"}],"identifier":"text-editor","label":"Text Editor","html_id":"text-editor","implicit":true,"key":"GgAlyjN1Nj"},{"type":"paragraph","position":{"start":{"line":3,"column":1},"end":{"line":4,"column":1}},"children":[{"type":"text","value":"Click on the “Text File” button in the Launcher.\nSelect the File Browser tab to see the new file ","position":{"start":{"line":3,"column":1},"end":{"line":3,"column":1}},"key":"jvvmP0y9rw"},{"type":"inlineCode","value":"untitled.txt","position":{"start":{"line":3,"column":1},"end":{"line":3,"column":1}},"key":"vnU0WoswSm"},{"type":"text","value":" you created.","position":{"start":{"line":3,"column":1},"end":{"line":3,"column":1}},"key":"uype6ZHuHZ"}],"key":"MZaZXeDLiq"},{"type":"paragraph","position":{"start":{"line":6,"column":1},"end":{"line":6,"column":1}},"children":[{"type":"text","value":"Enter this Python code into the new text file:","position":{"start":{"line":6,"column":1},"end":{"line":6,"column":1}},"key":"EEFyicH4l9"}],"key":"IKmwfM9V4i"},{"type":"code","lang":"python","value":"s = 'Hello, World!'\nprint(s)","position":{"start":{"line":7,"column":1},"end":{"line":10,"column":1}},"identifier":"udccs37ihk7s-code","enumerator":"6","html_id":"udccs37ihk7s-code","key":"SpxQzECWlS"},{"type":"paragraph","position":{"start":{"line":12,"column":1},"end":{"line":12,"column":1}},"children":[{"type":"text","value":"You may notice that the file has a dot instead of an “X” where you’d close it. This indicates that the file hasn’t been saved or has unsaved changes. Save the file (“command+s” on Mac, “control+s” on Windows, or “File▶Save Text”).","position":{"start":{"line":12,"column":1},"end":{"line":12,"column":1}},"key":"wFKDP8rHMb"}],"key":"n4KOSIUlzQ"},{"type":"paragraph","position":{"start":{"line":14,"column":1},"end":{"line":14,"column":1}},"children":[{"type":"text","value":"Go to the File Browser tab, right-click the new file we created and “Rename” it to ","position":{"start":{"line":14,"column":1},"end":{"line":14,"column":1}},"key":"KpVf4IkYHg"},{"type":"inlineCode","value":"hello.py","position":{"start":{"line":14,"column":1},"end":{"line":14,"column":1}},"key":"nMSN83rzpL"},{"type":"text","value":". Once the extension changes to ","position":{"start":{"line":14,"column":1},"end":{"line":14,"column":1}},"key":"fUlJxANpjy"},{"type":"inlineCode","value":".py","position":{"start":{"line":14,"column":1},"end":{"line":14,"column":1}},"key":"lOIUBAZVqY"},{"type":"text","value":", Jupyter recognizes that this is a Python file, and the text editor highlights the code based on Python syntax.","position":{"start":{"line":14,"column":1},"end":{"line":14,"column":1}},"key":"JFefsS4opk"}],"key":"HNfZEyFRQr"},{"type":"paragraph","position":{"start":{"line":16,"column":1},"end":{"line":16,"column":1}},"children":[{"type":"text","value":"Now, click the “+” button in the File Browser to create a new Launcher. In the Launcher tab, click on the “Terminal” button again to create a terminal. Now you have 2 tabs open: a text editor tab and a terminal tab. Drag the Terminal tab to the right side of the main work area to view both windows simultaneously. Click the File Browser tab to collapse the left sidebar and get more real estate! Alternatively, you could stack the windows one on top of the other.","position":{"start":{"line":16,"column":1},"end":{"line":16,"column":1}},"key":"uAHw3a6YYx"}],"key":"bDjPr919pd"},{"type":"paragraph","position":{"start":{"line":18,"column":1},"end":{"line":18,"column":1}},"children":[{"type":"text","value":"Run ","position":{"start":{"line":18,"column":1},"end":{"line":18,"column":1}},"key":"LSiKoX0z55"},{"type":"inlineCode","value":"ls","position":{"start":{"line":18,"column":1},"end":{"line":18,"column":1}},"key":"UniAAOiAgW"},{"type":"text","value":" in the Terminal window to see the text file we just created. Execute ","position":{"start":{"line":18,"column":1},"end":{"line":18,"column":1}},"key":"BcXLhFPbkN"},{"type":"inlineCode","value":"python hello.py","position":{"start":{"line":18,"column":1},"end":{"line":18,"column":1}},"key":"yecJviFZ9T"},{"type":"text","value":" in the Terminal window. See the output in the Terminal window.","position":{"start":{"line":18,"column":1},"end":{"line":18,"column":1}},"key":"sexaKwXlFh"}],"key":"wtZMMUA97T"},{"type":"image","url":"/pythia-foundations/build/txt-editor-a3a44f41aafdc36667b97d9fc07fb89d.png","alt":"Text Editor","position":{"start":{"line":20,"column":1},"end":{"line":20,"column":1}},"key":"IQZHS4SCCb","urlSource":"../images/txt-editor.png"},{"type":"paragraph","position":{"start":{"line":22,"column":1},"end":{"line":22,"column":1}},"children":[{"type":"text","value":"Now, let’s close the Terminal tab and shut down the Terminal in the Running Kernels tab (or execute “exit” in the Terminal itself). You should just have the Text editor window open; now we’re ready to look at Jupyter Notebooks.","position":{"start":{"line":22,"column":1},"end":{"line":22,"column":1}},"key":"tGJenhuc8w"}],"key":"hsQ72RtqCv"}],"identifier":"udccs37ihk7s","label":"UDCCs37IhK7S","html_id":"udccs37ihk7s","key":"lFDesp9oBS"},{"type":"block","kind":"notebook-content","data":{"id":"b0Zv8pF8e7Y0"},"children":[{"type":"heading","depth":2,"position":{"start":{"line":1,"column":1},"end":{"line":1,"column":1}},"children":[{"type":"text","value":"Running JupyterLab Notebooks","position":{"start":{"line":1,"column":1},"end":{"line":1,"column":1}},"key":"jTS2dqbH3b"}],"identifier":"running-jupyterlab-notebooks","label":"Running JupyterLab Notebooks","html_id":"running-jupyterlab-notebooks","implicit":true,"key":"UQuQXi7l1a"},{"type":"paragraph","position":{"start":{"line":3,"column":1},"end":{"line":3,"column":1}},"children":[{"type":"text","value":"There are two ways to open a Jupyter Notebook. One way is to select the File Browser Tab, click the “New Launcher” button, and select a Python 3 Notebook from the Launcher. Another way is to go to the top Menu Bar and select “File▶New▶Notebook”. JupyterLab will prompt you with a dialogue box to select the Kernel you want to use in your Notebook. Select the “Python 3” kernel.","position":{"start":{"line":3,"column":1},"end":{"line":3,"column":1}},"key":"kMfxktC3uM"}],"key":"PA15bN7zu5"},{"type":"paragraph","position":{"start":{"line":5,"column":1},"end":{"line":5,"column":1}},"children":[{"type":"text","value":"If you have the File Browser Tab open, notice you just created a file called ","position":{"start":{"line":5,"column":1},"end":{"line":5,"column":1}},"key":"CygBCzvj4F"},{"type":"inlineCode","value":"Untitled.ipynb.","position":{"start":{"line":5,"column":1},"end":{"line":5,"column":1}},"key":"Sk1lCsMPGK"},{"type":"text","value":" You will also have a new window open in the main work area for your new Notebook.","position":{"start":{"line":5,"column":1},"end":{"line":5,"column":1}},"key":"kBZgEBqKnz"}],"key":"mqEXXzKFxO"},{"type":"paragraph","position":{"start":{"line":7,"column":1},"end":{"line":7,"column":1}},"children":[{"type":"text","value":"Let’s explore the Notebook interface:","position":{"start":{"line":7,"column":1},"end":{"line":7,"column":1}},"key":"DPBS2vj5dG"}],"key":"Tt1WjjjIuR"},{"type":"paragraph","position":{"start":{"line":9,"column":1},"end":{"line":9,"column":1}},"children":[{"type":"text","value":"There is a ","position":{"start":{"line":9,"column":1},"end":{"line":9,"column":1}},"key":"C4BPtniRfZ"},{"type":"strong","position":{"start":{"line":9,"column":1},"end":{"line":9,"column":1}},"children":[{"type":"text","value":"Toolbar","position":{"start":{"line":9,"column":1},"end":{"line":9,"column":1}},"key":"jj7VLk2cv0"}],"key":"uiLjH0DofF"},{"type":"text","value":" at the top with buttons that allow you to Save, Create New Cells, Cut/Paste/Copy Cells, Run the Cell, Stop the Kernel, and Refresh the Kernel. There is also a ","position":{"start":{"line":9,"column":1},"end":{"line":9,"column":1}},"key":"nhSNMhNg4k"},{"type":"strong","position":{"start":{"line":9,"column":1},"end":{"line":9,"column":1}},"children":[{"type":"text","value":"dropdown menu","position":{"start":{"line":9,"column":1},"end":{"line":9,"column":1}},"key":"c9PavVIiqq"}],"key":"UYy4z5rWmA"},{"type":"text","value":" to select the kind of cell (Markdown, Raw, or Code). All the way to the right is the name of your Kernel (which you can click to change Kernels) and a ","position":{"start":{"line":9,"column":1},"end":{"line":9,"column":1}},"key":"VU2qz9EivM"},{"type":"strong","position":{"start":{"line":9,"column":1},"end":{"line":9,"column":1}},"children":[{"type":"text","value":"Kernel Status Icon","position":{"start":{"line":9,"column":1},"end":{"line":9,"column":1}},"key":"rITTZSzy1z"}],"key":"hDl5EurOeU"},{"type":"text","value":" that indicates if something is being computed by the Kernel (by a dark circle) or not (by an empty circle).","position":{"start":{"line":9,"column":1},"end":{"line":9,"column":1}},"key":"Y2N3lfoHTx"}],"key":"ATS2Z7kZVU"},{"type":"paragraph","position":{"start":{"line":11,"column":1},"end":{"line":11,"column":1}},"children":[{"type":"text","value":"Below the Toolbar is the Notebook itself. You should see an empty cell at the top of the Notebook. This should look similar to the layout of the Console.","position":{"start":{"line":11,"column":1},"end":{"line":11,"column":1}},"key":"La7HNPqgxn"}],"key":"X3MwHcaBN3"},{"type":"paragraph","position":{"start":{"line":13,"column":1},"end":{"line":14,"column":1}},"children":[{"type":"text","value":"The cell can be in 1 of 2 modes:  command mode or edit mode.\nIf your cell is grayed out and you can’t see a blinking cursor in the cell, then the cell is in command mode. We’ll talk about command mode more later. Click inside the box, and the cell will turn white with a blinking cursor inside it; the cell is now in edit mode. The mode is also listed on the info bar at the bottom of the page. The cell is selected if the blue bar is on the left side of the cell.","position":{"start":{"line":13,"column":1},"end":{"line":13,"column":1}},"key":"KRA2GMKxXO"}],"key":"vc9U4ED84e"},{"type":"image","url":"/pythia-foundations/build/notebook-interface_l-60cd07a9710555819702290f154644af.png","alt":"Notebook Interface","position":{"start":{"line":16,"column":1},"end":{"line":16,"column":1}},"key":"wOY1oMdoNn","urlSource":"../images/notebook-interface_labeled.png"},{"type":"paragraph","position":{"start":{"line":18,"column":1},"end":{"line":18,"column":1}},"children":[{"type":"text","value":"You may move the Notebook over so you can see your text file at the same time to compare, resizing the Notebook window as needed.","position":{"start":{"line":18,"column":1},"end":{"line":18,"column":1}},"key":"nr6aHb5Tkv"}],"key":"nmuSHsUkU0"}],"identifier":"b0zv8pf8e7y0","label":"b0Zv8pF8e7Y0","html_id":"b0zv8pf8e7y0","key":"t3VIeVG2on"},{"type":"block","kind":"notebook-content","data":{"id":"Dl5dbdlPwmLk"},"children":[{"type":"heading","depth":3,"position":{"start":{"line":1,"column":1},"end":{"line":1,"column":1}},"children":[{"type":"text","value":"Code Cells","position":{"start":{"line":1,"column":1},"end":{"line":1,"column":1}},"key":"gC2wAXDHbW"}],"identifier":"code-cells","label":"Code Cells","html_id":"code-cells","implicit":true,"key":"o57lLQhoIH"},{"type":"paragraph","position":{"start":{"line":2,"column":1},"end":{"line":3,"column":1}},"children":[{"type":"text","value":"Click inside the first cell of the Notebook to switch the cell to edit mode.\nEnter the following into the cell:","position":{"start":{"line":2,"column":1},"end":{"line":2,"column":1}},"key":"qNGyGkNVLk"}],"key":"SkouGi2mqW"},{"type":"code","lang":"python","value":"print(2+2)","position":{"start":{"line":5,"column":1},"end":{"line":7,"column":1}},"identifier":"dl5dbdlpwmlk-code-0","enumerator":"7","html_id":"dl5dbdlpwmlk-code-0","key":"wetWEq8Kiu"},{"type":"paragraph","position":{"start":{"line":9,"column":1},"end":{"line":9,"column":1}},"children":[{"type":"text","value":"Then type ","position":{"start":{"line":9,"column":1},"end":{"line":9,"column":1}},"key":"afqR6Q40zx"},{"type":"keyboard","children":[{"type":"text","value":"Shift","key":"jNMt7KmAJC"}],"key":"Qetmsxkab4"},{"type":"text","value":"+","position":{"start":{"line":9,"column":1},"end":{"line":9,"column":1}},"key":"Pl1BG0NhRs"},{"type":"keyboard","children":[{"type":"text","value":"Enter","key":"zSXrDrYPAs"}],"key":"VnNjQ8fwAZ"},{"type":"text","value":" to execute the cell.","position":{"start":{"line":9,"column":1},"end":{"line":9,"column":1}},"key":"pzsdJV3RsS"}],"key":"hc6JdAfqoC"},{"type":"paragraph","position":{"start":{"line":11,"column":1},"end":{"line":11,"column":1}},"children":[{"type":"text","value":"You’ll see the output, ","position":{"start":{"line":11,"column":1},"end":{"line":11,"column":1}},"key":"ruzalbDkm9"},{"type":"inlineCode","value":"4","position":{"start":{"line":11,"column":1},"end":{"line":11,"column":1}},"key":"SflpRnihER"},{"type":"text","value":", printed directly below your code cell. Executing the cell automatically creates a new cell in edit mode below the first.","position":{"start":{"line":11,"column":1},"end":{"line":11,"column":1}},"key":"zp0lHjyciv"}],"key":"gOWPcjEnvv"},{"type":"paragraph","position":{"start":{"line":13,"column":1},"end":{"line":13,"column":1}},"children":[{"type":"text","value":"In this new cell, enter:","position":{"start":{"line":13,"column":1},"end":{"line":13,"column":1}},"key":"jgwFw2vgpY"}],"key":"sV5MEuQuWa"},{"type":"code","lang":"python","value":"for i in range(4):\n    print(i) ","position":{"start":{"line":15,"column":1},"end":{"line":18,"column":1}},"identifier":"dl5dbdlpwmlk-code-1","enumerator":"8","html_id":"dl5dbdlpwmlk-code-1","key":"pKzJiKurCu"},{"type":"paragraph","position":{"start":{"line":20,"column":1},"end":{"line":20,"column":1}},"children":[{"type":"text","value":"Execute the cell. A Jupyter code cell can run multiple lines of code; each Jupyter code cell can even contain a complete Python program!","position":{"start":{"line":20,"column":1},"end":{"line":20,"column":1}},"key":"bT9tVfRfOU"}],"key":"LSf8Kk2zg4"},{"type":"paragraph","position":{"start":{"line":22,"column":1},"end":{"line":22,"column":1}},"children":[{"type":"text","value":"To demonstrate how to import code that you have written in a ","position":{"start":{"line":22,"column":1},"end":{"line":22,"column":1}},"key":"LwPNzBZNZq"},{"type":"inlineCode","value":".py","position":{"start":{"line":22,"column":1},"end":{"line":22,"column":1}},"key":"pCQOc9MpB5"},{"type":"text","value":" file, enter the following into the next cell:","position":{"start":{"line":22,"column":1},"end":{"line":22,"column":1}},"key":"QN01IOzi0X"}],"key":"pdzBrBtpnV"},{"type":"code","lang":"python","value":"import hello","position":{"start":{"line":24,"column":1},"end":{"line":26,"column":1}},"identifier":"dl5dbdlpwmlk-code-2","enumerator":"9","html_id":"dl5dbdlpwmlk-code-2","key":"AaYISXVQlX"},{"type":"paragraph","position":{"start":{"line":28,"column":1},"end":{"line":28,"column":1}},"children":[{"type":"text","value":"Then type ","position":{"start":{"line":28,"column":1},"end":{"line":28,"column":1}},"key":"dyn3XfYIPS"},{"type":"keyboard","children":[{"type":"text","value":"Shift","key":"uttOmB0Q6f"}],"key":"j5BUmoUJpr"},{"type":"text","value":"+","position":{"start":{"line":28,"column":1},"end":{"line":28,"column":1}},"key":"XLjzQudaD9"},{"type":"keyboard","children":[{"type":"text","value":"Enter","key":"CGj6bmYNwt"}],"key":"lofRvPnoii"},{"type":"text","value":".","position":{"start":{"line":28,"column":1},"end":{"line":28,"column":1}},"key":"N2bLlKkHui"}],"key":"fyQXLUUsRE"},{"type":"paragraph","position":{"start":{"line":30,"column":1},"end":{"line":30,"column":1}},"children":[{"type":"text","value":"This single-line ","position":{"start":{"line":30,"column":1},"end":{"line":30,"column":1}},"key":"zAsEfVXBEe"},{"type":"inlineCode","value":"import","position":{"start":{"line":30,"column":1},"end":{"line":30,"column":1}},"key":"kNAD9BSsZZ"},{"type":"text","value":" statement runs the contents of your ","position":{"start":{"line":30,"column":1},"end":{"line":30,"column":1}},"key":"DEeDO6Ib0P"},{"type":"inlineCode","value":"hello.py","position":{"start":{"line":30,"column":1},"end":{"line":30,"column":1}},"key":"DnOby5JO8V"},{"type":"text","value":" script file, and would do the same for any file regardless of length.","position":{"start":{"line":30,"column":1},"end":{"line":30,"column":1}},"key":"oZwakkI4Q1"}],"key":"hmDwg44Lu7"},{"type":"div","class":"admonition alert alert-warning","children":[{"type":"paragraph","children":[{"type":"text","value":"Warning","key":"fOY0Qbo30k"}],"key":"BSRrfzzNLK"},{"type":"text","value":"It is generally considered bad practice to include any output in a “.py” file meant to be imported and used within different Python scripts. Such a file should contain only function and class definitions.","key":"fwMEcyg2Y8"}],"key":"zgusRTqsSM"},{"type":"paragraph","children":[{"type":"text","value":"You've executed the cell with the Python 3 kernel, and it spit out the output, “Hello, World!” Since you've imported the `hello.py` module into the Notebook’s kernel runtime, you can now directly look at the variable “s” in this second cell. Enter the following in the next cell:","key":"geGo6NPDda"}],"key":"yv7NU9AmBu"},{"type":"code","lang":"python","value":"hello.s","position":{"start":{"line":39,"column":1},"end":{"line":41,"column":1}},"identifier":"dl5dbdlpwmlk-code-3","enumerator":"10","html_id":"dl5dbdlpwmlk-code-3","key":"ABIglmqRhI"},{"type":"paragraph","position":{"start":{"line":43,"column":1},"end":{"line":43,"column":1}},"children":[{"type":"text","value":"Hit ","position":{"start":{"line":43,"column":1},"end":{"line":43,"column":1}},"key":"YXtn1vY3U3"},{"type":"keyboard","children":[{"type":"text","value":"Shift","key":"kW5HZDpVZW"}],"key":"voZZmGSWEz"},{"type":"text","value":"+","position":{"start":{"line":43,"column":1},"end":{"line":43,"column":1}},"key":"ajgwWQ0EMv"},{"type":"keyboard","children":[{"type":"text","value":"Enter","key":"Bo1Z3focFt"}],"key":"tNkGslKEnt"},{"type":"text","value":" to execute.","position":{"start":{"line":43,"column":1},"end":{"line":43,"column":1}},"key":"YxZwGoDvTd"}],"key":"mPvRF8XSmz"},{"type":"paragraph","position":{"start":{"line":45,"column":1},"end":{"line":45,"column":1}},"children":[{"type":"text","value":"Again, it displays the value of the variable ","position":{"start":{"line":45,"column":1},"end":{"line":45,"column":1}},"key":"LgaojdSXBb"},{"type":"inlineCode","value":"s","position":{"start":{"line":45,"column":1},"end":{"line":45,"column":1}},"key":"KlrLaO4PKB"},{"type":"text","value":" from the “hello” module we just created. One difference is that this time the output is given its own label ","position":{"start":{"line":45,"column":1},"end":{"line":45,"column":1}},"key":"sgTV1Bu0Av"},{"type":"inlineCode","value":"[2]","position":{"start":{"line":45,"column":1},"end":{"line":45,"column":1}},"key":"JHNqOBQ56Q"},{"type":"text","value":" matching the input label of the cell (whereas the output from cell ","position":{"start":{"line":45,"column":1},"end":{"line":45,"column":1}},"key":"CRtoGFaRK7"},{"type":"inlineCode","value":"[1]","position":{"start":{"line":45,"column":1},"end":{"line":45,"column":1}},"key":"etRjXD9GSN"},{"type":"text","value":" is not labelled).  This is the difference between output sent to the screen vs. the return value of the cell.","position":{"start":{"line":45,"column":1},"end":{"line":45,"column":1}},"key":"NcVMcfq5Sz"}],"key":"YE76BQq8FK"},{"type":"paragraph","position":{"start":{"line":47,"column":1},"end":{"line":47,"column":1}},"children":[{"type":"text","value":"Let’s now import a module from the Python standard library:","position":{"start":{"line":47,"column":1},"end":{"line":47,"column":1}},"key":"zeAd3v9FAm"}],"key":"vIrjiGqYuU"},{"type":"code","lang":"python","value":"import time\ntime.sleep(10)","position":{"start":{"line":49,"column":1},"end":{"line":52,"column":1}},"identifier":"dl5dbdlpwmlk-code-4","enumerator":"11","html_id":"dl5dbdlpwmlk-code-4","key":"jzcjcrBTmW"},{"type":"paragraph","position":{"start":{"line":54,"column":1},"end":{"line":54,"column":1}},"children":[{"type":"text","value":"Again, hit ","position":{"start":{"line":54,"column":1},"end":{"line":54,"column":1}},"key":"HMUelDaIN2"},{"type":"keyboard","children":[{"type":"text","value":"Shift","key":"kAlUOnfF9D"}],"key":"prdNAkSWMc"},{"type":"text","value":"+","position":{"start":{"line":54,"column":1},"end":{"line":54,"column":1}},"key":"l3HeYVCPPZ"},{"type":"keyboard","children":[{"type":"text","value":"Enter","key":"f9o98fOhK5"}],"key":"rmf2Ck4VOa"},{"type":"text","value":".","position":{"start":{"line":54,"column":1},"end":{"line":54,"column":1}},"key":"AQFlY2EhGg"}],"key":"jnjTwKcnTQ"},{"type":"paragraph","position":{"start":{"line":56,"column":1},"end":{"line":56,"column":1}},"children":[{"type":"text","value":"The ","position":{"start":{"line":56,"column":1},"end":{"line":56,"column":1}},"key":"MeWiDFmHgG"},{"type":"inlineCode","value":"time.sleep(10)","position":{"start":{"line":56,"column":1},"end":{"line":56,"column":1}},"key":"PDZGo0HIiR"},{"type":"text","value":" function causes code to wait for 10 seconds, which is plenty of time to notice how the cell changes in time:","position":{"start":{"line":56,"column":1},"end":{"line":56,"column":1}},"key":"KcwACltY7m"}],"key":"o4MuV5GrA7"},{"type":"list","ordered":false,"spread":false,"position":{"start":{"line":57,"column":1},"end":{"line":59,"column":1}},"children":[{"type":"listItem","spread":true,"position":{"start":{"line":57,"column":1},"end":{"line":57,"column":1}},"children":[{"type":"text","value":"The label of the cell is ","position":{"start":{"line":57,"column":1},"end":{"line":57,"column":1}},"key":"B4Oqi211Ey"},{"type":"inlineCode","value":"[*]","position":{"start":{"line":57,"column":1},"end":{"line":57,"column":1}},"key":"UQJhuDInhR"},{"type":"text","value":", indicating that the kernel is running that cell","position":{"start":{"line":57,"column":1},"end":{"line":57,"column":1}},"key":"DkzmEXo0Ey"}],"key":"w2XsuYinm4"},{"type":"listItem","spread":true,"position":{"start":{"line":58,"column":1},"end":{"line":59,"column":1}},"children":[{"type":"text","value":"In the top right corner of the Notebook, the status icon is a filled-in circle, indicating that the kernel is running","position":{"start":{"line":58,"column":1},"end":{"line":58,"column":1}},"key":"fIMfMdORH0"}],"key":"K6hXrrH8I9"}],"key":"ziZhXFS7wF"},{"type":"paragraph","position":{"start":{"line":60,"column":1},"end":{"line":60,"column":1}},"children":[{"type":"text","value":"After 10 seconds, the cell completes running, the label is updated to ","position":{"start":{"line":60,"column":1},"end":{"line":60,"column":1}},"key":"hH9DMQOdAe"},{"type":"inlineCode","value":"[3], and the status icon returns to the “empty circle” state. If you rerun the cell, the label will update to ","position":{"start":{"line":60,"column":1},"end":{"line":60,"column":1}},"key":"BNUYdPaOi9"},{"type":"text","value":"[4]`.","position":{"start":{"line":60,"column":1},"end":{"line":60,"column":1}},"key":"K90DDhgWiB"}],"key":"MG8kpaEwp2"},{"type":"image","url":"/pythia-foundations/build/codecells-48528980152b28fb0e26731112c44441.png","alt":"Code Cells","position":{"start":{"line":62,"column":1},"end":{"line":62,"column":1}},"key":"zMlNpo4yVe","urlSource":"../images/codecells.png"}],"identifier":"dl5dbdlpwmlk","label":"Dl5dbdlPwmLk","html_id":"dl5dbdlpwmlk","key":"tJVVvagDJY"},{"type":"block","kind":"notebook-content","data":{"id":"DTSoIqjAM4sg","jp-MarkdownHeadingCollapsed":true,"tags":[]},"children":[{"type":"heading","depth":3,"position":{"start":{"line":1,"column":1},"end":{"line":1,"column":1}},"children":[{"type":"text","value":"Markdown Cells","position":{"start":{"line":1,"column":1},"end":{"line":1,"column":1}},"key":"wFb0g2vSzL"}],"identifier":"markdown-cells","label":"Markdown Cells","html_id":"markdown-cells","implicit":true,"key":"yCCPozMHoK"},{"type":"paragraph","position":{"start":{"line":2,"column":1},"end":{"line":3,"column":1}},"children":[{"type":"text","value":"Now, with the next cell selected (i.e., the blue bar appears to the left of the cell), whether in edit or command mode, go up to the “cell type” dropdown menu above and select “Markdown”.\nNotice that the ","position":{"start":{"line":2,"column":1},"end":{"line":2,"column":1}},"key":"UwK1unaXJf"},{"type":"inlineCode","value":"[ ]","position":{"start":{"line":2,"column":1},"end":{"line":2,"column":1}},"key":"L1lBnBmaIt"},{"type":"text","value":" label goes away.","position":{"start":{"line":2,"column":1},"end":{"line":2,"column":1}},"key":"US1RfjQnWe"}],"key":"RTG2bgarNL"},{"type":"paragraph","position":{"start":{"line":5,"column":1},"end":{"line":6,"column":1}},"children":[{"type":"text","value":"Markdown is a markup language that allows you to format text in a plain-text editor. Here we will demonstrate some common Markdown syntax. You can learn more at ","position":{"start":{"line":5,"column":1},"end":{"line":5,"column":1}},"key":"GEaFCi1wTC"},{"type":"link","url":"https://www.markdownguide.org/","position":{"start":{"line":5,"column":1},"end":{"line":5,"column":1}},"children":[{"type":"text","value":"the Markdown Guide site","position":{"start":{"line":5,"column":1},"end":{"line":5,"column":1}},"key":"f6IUWHgfvD"}],"urlSource":"https://www.markdownguide.org/","key":"HDxFpFLde5"},{"type":"text","value":" or in our ","position":{"start":{"line":5,"column":1},"end":{"line":5,"column":1}},"key":"u5ev2O4fvc"},{"type":"link","url":"https://foundations.projectpythia.org/foundations/markdown.html","position":{"start":{"line":5,"column":1},"end":{"line":5,"column":1}},"children":[{"type":"text","value":"Getting Started with Jupyter: Markdown","position":{"start":{"line":5,"column":1},"end":{"line":5,"column":1}},"key":"IXIPEl3bse"}],"urlSource":"https://foundations.projectpythia.org/foundations/markdown.html","key":"aD5233vBiN"},{"type":"text","value":" content.\nClick on the cell and enter edit mode; we can now type in some markdown text like so:","position":{"start":{"line":5,"column":1},"end":{"line":5,"column":1}},"key":"ySQN3t1rSy"}],"key":"BV1tngNke7"},{"type":"code","lang":"markdown","value":"# This is a heading!\nAnd this is some text.\n\n## And this is a subheading\nwith a bulleted list in it:\n\n - one\n - two\n - three","position":{"start":{"line":8,"column":1},"end":{"line":18,"column":1}},"identifier":"dtsoiqjam4sg-code-0","enumerator":"12","html_id":"dtsoiqjam4sg-code-0","key":"j0ZQkMDbzs"},{"type":"paragraph","position":{"start":{"line":20,"column":1},"end":{"line":20,"column":1}},"children":[{"type":"text","value":"Then press ","position":{"start":{"line":20,"column":1},"end":{"line":20,"column":1}},"key":"lLxNi9Mgna"},{"type":"keyboard","children":[{"type":"text","value":"Shift","key":"YTMwKgcVwQ"}],"key":"YNTUbl1Wu2"},{"type":"text","value":"+","position":{"start":{"line":20,"column":1},"end":{"line":20,"column":1}},"key":"SNQrgsXErZ"},{"type":"keyboard","children":[{"type":"text","value":"Enter","key":"DBxJeHzfYw"}],"key":"GjaUrRlHpD"},{"type":"text","value":" to render the markdown to HTML.","position":{"start":{"line":20,"column":1},"end":{"line":20,"column":1}},"key":"ZDoQn5TQ89"}],"key":"eArGbdxFLd"},{"type":"image","url":"/pythia-foundations/build/markdown-e52bd8a419c6fe21e9afa95af10e6997.png","key":"A7psqWNocp","urlSource":"../images/markdown.png"},{"type":"paragraph","position":{"start":{"line":24,"column":1},"end":{"line":24,"column":1}},"children":[{"type":"text","value":"Again, in the next cell, change the cell type to “Markdown”. To demonstrate displaying equations, enter:","position":{"start":{"line":24,"column":1},"end":{"line":24,"column":1}},"key":"wIRxeFXdmS"}],"key":"upcC6dMfhO"},{"type":"code","lang":"markdown","value":"## Some math\n\nAnd Jupyter’s version of markdown can display LaTeX:\n\n$$\ne^x=\\sum_{i=0}^{\\infty} \\frac{1}{i!}x^i\n$$","position":{"start":{"line":26,"column":1},"end":{"line":34,"column":1}},"identifier":"dtsoiqjam4sg-code-1","enumerator":"13","html_id":"dtsoiqjam4sg-code-1","key":"ONuSfk6LAH"},{"type":"paragraph","position":{"start":{"line":36,"column":1},"end":{"line":36,"column":1}},"children":[{"type":"text","value":"When you are done, type ","position":{"start":{"line":36,"column":1},"end":{"line":36,"column":1}},"key":"UrvIfr8xVE"},{"type":"keyboard","children":[{"type":"text","value":"Shift","key":"UA8Q8kTNRD"}],"key":"KGBklTsohv"},{"type":"text","value":"+","position":{"start":{"line":36,"column":1},"end":{"line":36,"column":1}},"key":"lHPZcz9KTp"},{"type":"keyboard","children":[{"type":"text","value":"Enter","key":"oyzz5jM4uz"}],"key":"K2qSffni8L"},{"type":"text","value":" to render the markdown document.","position":{"start":{"line":36,"column":1},"end":{"line":36,"column":1}},"key":"EketrQPNpk"}],"key":"YcwPyqN15J"},{"type":"image","url":"/pythia-foundations/build/markdown_eq-36095adefc283a5673786c11f96cdbaf.png","key":"JfMMRhsWvW","urlSource":"../images/markdown_eq.png"},{"type":"paragraph","position":{"start":{"line":40,"column":1},"end":{"line":40,"column":1}},"children":[{"type":"text","value":"You can also do inline equations with a single “$”, for example","position":{"start":{"line":40,"column":1},"end":{"line":40,"column":1}},"key":"bk6tIDCjPr"}],"key":"l9gxeFSR5X"},{"type":"code","lang":"markdown","value":"This is an equation: $i^4$.","position":{"start":{"line":42,"column":1},"end":{"line":44,"column":1}},"identifier":"dtsoiqjam4sg-code-2","enumerator":"14","html_id":"dtsoiqjam4sg-code-2","key":"nH6jsnai4A"},{"type":"image","url":"/pythia-foundations/build/markdown_eq_inline-0b9479ed7b98f697e34c4fe99d21b5ac.png","key":"Xexw6fn6KM","urlSource":"../images/markdown_eq_inline.png"},{"type":"paragraph","position":{"start":{"line":48,"column":1},"end":{"line":48,"column":1}},"children":[{"type":"text","value":"Note that the “markdown” source code is rendered into much prettier text, which we can take advantage of for narrating our work in the Notebook!","position":{"start":{"line":48,"column":1},"end":{"line":48,"column":1}},"key":"vkIoVIxfkA"}],"key":"hyqDrY0N4G"}],"identifier":"dtsoiqjam4sg","label":"DTSoIqjAM4sg","html_id":"dtsoiqjam4sg","visibility":"show","key":"zInHLYruHd"},{"type":"block","kind":"notebook-content","data":{"id":"DPP39honNHSh","jp-MarkdownHeadingCollapsed":true,"tags":[]},"children":[{"type":"heading","depth":3,"position":{"start":{"line":1,"column":1},"end":{"line":1,"column":1}},"children":[{"type":"text","value":"Raw Cells","position":{"start":{"line":1,"column":1},"end":{"line":1,"column":1}},"key":"okTugKkyeM"}],"identifier":"raw-cells","label":"Raw Cells","html_id":"raw-cells","implicit":true,"key":"HH3YShLKqM"},{"type":"paragraph","position":{"start":{"line":3,"column":1},"end":{"line":3,"column":1}},"children":[{"type":"text","value":"Now in a new cell selected, select “raw” from the “cell type” dropdown menu. Again, the ","position":{"start":{"line":3,"column":1},"end":{"line":3,"column":1}},"key":"fPgbSW4Syp"},{"type":"inlineCode","value":"[ ]","position":{"start":{"line":3,"column":1},"end":{"line":3,"column":1}},"key":"PChJzx94dc"},{"type":"text","value":" label goes away, and you can enter the following in the cell:","position":{"start":{"line":3,"column":1},"end":{"line":3,"column":1}},"key":"dZuuKqejXo"}],"key":"tQYkIsjMNl"},{"type":"code","lang":"text","value":"i = 8\nprint(i)","position":{"start":{"line":5,"column":1},"end":{"line":8,"column":1}},"identifier":"dpp39honnhsh-code","enumerator":"15","html_id":"dpp39honnhsh-code","key":"QCOwH0LTsE"},{"type":"paragraph","position":{"start":{"line":10,"column":1},"end":{"line":10,"column":1}},"children":[{"type":"text","value":"When you ","position":{"start":{"line":10,"column":1},"end":{"line":10,"column":1}},"key":"N0RcVUzLCJ"},{"type":"keyboard","children":[{"type":"text","value":"Shift","key":"HvZUBAYMRH"}],"key":"Zvdp6AS25p"},{"type":"text","value":"+","position":{"start":{"line":10,"column":1},"end":{"line":10,"column":1}},"key":"R5Fi3c3r8M"},{"type":"keyboard","children":[{"type":"text","value":"Enter","key":"IVL5NhmEoW"}],"key":"S21PKwyPaP"},{"type":"text","value":" the text isn’t rendered.","position":{"start":{"line":10,"column":1},"end":{"line":10,"column":1}},"key":"KuuzvvlJik"}],"key":"MIvoOAt6Fd"},{"type":"paragraph","position":{"start":{"line":12,"column":1},"end":{"line":12,"column":1}},"children":[{"type":"text","value":"This is a way of entering text/source that you do not want the Notebook to do anything with (i.e., no rendering).","position":{"start":{"line":12,"column":1},"end":{"line":12,"column":1}},"key":"tl6ZeWT1Kp"}],"key":"dG6YVMsm01"},{"type":"image","url":"/pythia-foundations/build/raw-3912453c76583274dc9f33fdf7ee2a80.png","alt":"Raw","position":{"start":{"line":14,"column":1},"end":{"line":14,"column":1}},"key":"MGjVvYyvT5","urlSource":"../images/raw.png"}],"identifier":"dpp39honnhsh","label":"DPP39honNHSh","html_id":"dpp39honnhsh","visibility":"show","key":"ZQZ4uSaKiI"},{"type":"block","kind":"notebook-content","data":{"id":"N89Z7vdgNMKx"},"children":[{"type":"heading","depth":3,"position":{"start":{"line":1,"column":1},"end":{"line":1,"column":1}},"children":[{"type":"text","value":"Command Mode Shortcuts","position":{"start":{"line":1,"column":1},"end":{"line":1,"column":1}},"key":"drMCf8OsrC"}],"identifier":"command-mode-shortcuts","label":"Command Mode Shortcuts","html_id":"command-mode-shortcuts","implicit":true,"key":"Sgg1IcHjVf"},{"type":"paragraph","position":{"start":{"line":3,"column":1},"end":{"line":3,"column":1}},"children":[{"type":"text","value":"Now, select the “raw” cell you just created by clicking on the far left of the cell.","position":{"start":{"line":3,"column":1},"end":{"line":3,"column":1}},"key":"uzef4yReNM"}],"key":"t8FxFSAwCf"},{"type":"paragraph","position":{"start":{"line":5,"column":1},"end":{"line":5,"column":1}},"children":[{"type":"text","value":"You are now in “command mode”. The up and down arrows move to different cells. Don’t hit “enter” which would switch the cell to “edit mode.\" Let’s explore command mode.","position":{"start":{"line":5,"column":1},"end":{"line":5,"column":1}},"key":"W8wmUxuomR"}],"key":"hrf3PC7WRI"},{"type":"paragraph","position":{"start":{"line":7,"column":1},"end":{"line":7,"column":1}},"children":[{"type":"text","value":"You can change the cell type with ","position":{"start":{"line":7,"column":1},"end":{"line":7,"column":1}},"key":"Gjezfnwjq9"},{"type":"inlineCode","value":"y","position":{"start":{"line":7,"column":1},"end":{"line":7,"column":1}},"key":"WkgRb2uWZK"},{"type":"text","value":" for code, ","position":{"start":{"line":7,"column":1},"end":{"line":7,"column":1}},"key":"dRTb0T6glt"},{"type":"inlineCode","value":"m","position":{"start":{"line":7,"column":1},"end":{"line":7,"column":1}},"key":"kKW7JduBwm"},{"type":"text","value":" for markdown, or ","position":{"start":{"line":7,"column":1},"end":{"line":7,"column":1}},"key":"MWyWWXeqjJ"},{"type":"inlineCode","value":"r","position":{"start":{"line":7,"column":1},"end":{"line":7,"column":1}},"key":"sC4I4CQKH7"},{"type":"text","value":" for raw.","position":{"start":{"line":7,"column":1},"end":{"line":7,"column":1}},"key":"jo9NaQzbTE"}],"key":"cC2SygPNTl"},{"type":"paragraph","position":{"start":{"line":9,"column":1},"end":{"line":9,"column":1}},"children":[{"type":"text","value":"You can add a new cell above the selected cell with ","position":{"start":{"line":9,"column":1},"end":{"line":9,"column":1}},"key":"laZFoJ1XeZ"},{"type":"inlineCode","value":"a","position":{"start":{"line":9,"column":1},"end":{"line":9,"column":1}},"key":"sUG35CEpxc"},{"type":"text","value":" (or below the selected cell with ","position":{"start":{"line":9,"column":1},"end":{"line":9,"column":1}},"key":"gb4MEQgrt6"},{"type":"inlineCode","value":"b","position":{"start":{"line":9,"column":1},"end":{"line":9,"column":1}},"key":"FJIm0ZrzXP"},{"type":"text","value":").","position":{"start":{"line":9,"column":1},"end":{"line":9,"column":1}},"key":"HTlx1sFmj4"}],"key":"mbCdfgH0sq"},{"type":"paragraph","position":{"start":{"line":11,"column":1},"end":{"line":11,"column":1}},"children":[{"type":"text","value":"You can cut (","position":{"start":{"line":11,"column":1},"end":{"line":11,"column":1}},"key":"dZoiPYts51"},{"type":"inlineCode","value":"x","position":{"start":{"line":11,"column":1},"end":{"line":11,"column":1}},"key":"dYytZpkicQ"},{"type":"text","value":"), copy (","position":{"start":{"line":11,"column":1},"end":{"line":11,"column":1}},"key":"zM2SDOjNDo"},{"type":"inlineCode","value":"c","position":{"start":{"line":11,"column":1},"end":{"line":11,"column":1}},"key":"ao6ckVzNaf"},{"type":"text","value":"), and paste (","position":{"start":{"line":11,"column":1},"end":{"line":11,"column":1}},"key":"ujOrCZ4Rfl"},{"type":"inlineCode","value":"v","position":{"start":{"line":11,"column":1},"end":{"line":11,"column":1}},"key":"kYCDgRm5KZ"},{"type":"text","value":").","position":{"start":{"line":11,"column":1},"end":{"line":11,"column":1}},"key":"KzdFmjYIfK"}],"key":"ALglEOuaXY"},{"type":"paragraph","position":{"start":{"line":13,"column":1},"end":{"line":13,"column":1}},"children":[{"type":"text","value":"You can move a cell up or down by clicking and dragging.","position":{"start":{"line":13,"column":1},"end":{"line":13,"column":1}},"key":"nExEZ9tFsb"}],"key":"dwLTWTpY8M"},{"type":"div","class":"admonition alert alert-warning","children":[{"type":"paragraph","children":[{"type":"text","value":"Warning","key":"ivDXSAOYe6"}],"key":"N2x5GnKSx9"},{"type":"text","value":"Cells can be executed in any order you want. You just have to select the cell and ","key":"sNLhn62lYW"},{"type":"keyboard","children":[{"type":"text","value":"Shift","key":"mKQsW6tRHl"}],"key":"LefWUnEdBF"},{"type":"text","value":"+","key":"tWTUto7pih"},{"type":"keyboard","children":[{"type":"text","value":"Enter","key":"JuZywOnJNp"}],"key":"Za0UsFR44X"},{"type":"text","value":", and select the cells in any order you want. However, if you share your notebook, there is an implicit expectation to execute the cells in the order in which they are presented in the notebook. Be careful with this! If variables are reused or redefined between cells, reordering them could have unintended consequences!","key":"yP2N41wjnA"}],"key":"GOCdPta4I6"}],"identifier":"n89z7vdgnmkx","label":"N89Z7vdgNMKx","html_id":"n89z7vdgnmkx","key":"l7PnVB7t5s"},{"type":"block","kind":"notebook-content","data":{"id":"KySy3X-aauaR"},"children":[{"type":"heading","depth":3,"position":{"start":{"line":1,"column":1},"end":{"line":1,"column":1}},"children":[{"type":"text","value":"Special Variables","position":{"start":{"line":1,"column":1},"end":{"line":1,"column":1}},"key":"NtXwDWxf1g"}],"identifier":"special-variables","label":"Special Variables","html_id":"special-variables","implicit":true,"key":"moh1DIdRwZ"},{"type":"paragraph","position":{"start":{"line":3,"column":1},"end":{"line":3,"column":1}},"children":[{"type":"text","value":"Now, in the empty cell at the end, enter one underscore:","position":{"start":{"line":3,"column":1},"end":{"line":3,"column":1}},"key":"WgQq04sgDt"}],"key":"yxD2XCoDY4"},{"type":"code","lang":"","value":"_","position":{"start":{"line":5,"column":1},"end":{"line":7,"column":1}},"identifier":"kysy3x-aauar-code-0","enumerator":"16","html_id":"kysy3x-aauar-code-0","key":"lcB9K0PdMn"},{"type":"paragraph","position":{"start":{"line":9,"column":1},"end":{"line":9,"column":1}},"children":[{"type":"text","value":"This is a special character that means the last cell output.  Two underscores means the second to last cell output, and three underscores means the third to last output. You can also refer to the output by label with:","position":{"start":{"line":9,"column":1},"end":{"line":9,"column":1}},"key":"KczDURYGE3"}],"key":"yFzaXHuUTk"},{"type":"code","lang":"","value":"_2","position":{"start":{"line":11,"column":1},"end":{"line":13,"column":1}},"identifier":"kysy3x-aauar-code-1","enumerator":"17","html_id":"kysy3x-aauar-code-1","key":"bI2YkuVZyI"},{"type":"div","class":"admonition alert alert-danger","children":[{"type":"paragraph","children":[{"type":"text","value":"Danger","key":"J6jadXzyTq"}],"key":"vLB2HHCnb7"},{"type":"text","value":"If the cell you to refer to does not have a return value, this will raise an error.","key":"ZJCp6iDuuh"}],"key":"oYyOs6h9MB"},{"type":"paragraph","position":{"start":{"line":20,"column":1},"end":{"line":20,"column":1}},"children":[{"type":"text","value":"You can equivalently use the variables ","position":{"start":{"line":20,"column":1},"end":{"line":20,"column":1}},"key":"FwHD4W0DoX"},{"type":"inlineCode","value":"Out[2]","position":{"start":{"line":20,"column":1},"end":{"line":20,"column":1}},"key":"UuI8PfAQNr"},{"type":"text","value":" or ","position":{"start":{"line":20,"column":1},"end":{"line":20,"column":1}},"key":"gEwEvZzhZs"},{"type":"inlineCode","value":"In[2]","position":{"start":{"line":20,"column":1},"end":{"line":20,"column":1}},"key":"OOziSnqXjo"},{"type":"text","value":" to retrieve the output and input (as a string).","position":{"start":{"line":20,"column":1},"end":{"line":20,"column":1}},"key":"XPml96TIOe"}],"key":"s58WY6c8Xq"},{"type":"image","url":"/pythia-foundations/build/special_vars-0f287b6ba55cf83bc751a4094aa8f8e6.png","key":"a9alYhHf4X","urlSource":"../images/special_vars.png"}],"identifier":"kysy3x-aauar","label":"KySy3X-aauaR","html_id":"kysy3x-aauar","key":"rFCUIyPTbS"},{"type":"block","kind":"notebook-content","data":{"id":"F0wU5mU2blds"},"children":[{"type":"heading","depth":3,"position":{"start":{"line":1,"column":1},"end":{"line":1,"column":1}},"children":[{"type":"text","value":"Shell Commands","position":{"start":{"line":1,"column":1},"end":{"line":1,"column":1}},"key":"hGXHjLEEOr"}],"identifier":"shell-commands","label":"Shell Commands","html_id":"shell-commands","implicit":true,"key":"RyvLJKhuBj"},{"type":"paragraph","position":{"start":{"line":3,"column":1},"end":{"line":3,"column":1}},"children":[{"type":"text","value":"In the next code cell, enter the following:","position":{"start":{"line":3,"column":1},"end":{"line":3,"column":1}},"key":"aGTVxqb6cX"}],"key":"UQbGvT99wp"},{"type":"code","lang":"python","value":"!pwd","position":{"start":{"line":5,"column":1},"end":{"line":7,"column":1}},"identifier":"f0wu5mu2blds-code-0","enumerator":"18","html_id":"f0wu5mu2blds-code-0","key":"VMDvxtsjI4"},{"type":"paragraph","position":{"start":{"line":9,"column":1},"end":{"line":9,"column":1}},"children":[{"type":"text","value":"The ","position":{"start":{"line":9,"column":1},"end":{"line":9,"column":1}},"key":"f0gUiXE1iE"},{"type":"inlineCode","value":"!","position":{"start":{"line":9,"column":1},"end":{"line":9,"column":1}},"key":"rH9Cf9n0ys"},{"type":"text","value":" allows you to write shell commands. A shell command is a command that is run by the host operating system, not the Python kernel. Executing this cell will “print the working directory” (i.e. your current directory).","position":{"start":{"line":9,"column":1},"end":{"line":9,"column":1}},"key":"pCnzK8eC2p"}],"key":"rKDlByHNMu"},{"type":"paragraph","position":{"start":{"line":11,"column":1},"end":{"line":11,"column":1}},"children":[{"type":"text","value":"You can even use the output of shell commands as input to Python code. For example:","position":{"start":{"line":11,"column":1},"end":{"line":11,"column":1}},"key":"w5xHQElXVq"}],"key":"HAqYrRZKC3"},{"type":"code","lang":"python","value":"files = !ls\nprint(files)","position":{"start":{"line":13,"column":1},"end":{"line":16,"column":1}},"identifier":"f0wu5mu2blds-code-1","enumerator":"19","html_id":"f0wu5mu2blds-code-1","key":"yLcmio9GNS"}],"identifier":"f0wu5mu2blds","label":"F0wU5mU2blds","html_id":"f0wu5mu2blds","key":"EeOZCX3liL"},{"type":"block","kind":"notebook-content","data":{"id":"SLtXSO0bNRHC"},"children":[{"type":"heading","depth":3,"position":{"start":{"line":1,"column":1},"end":{"line":1,"column":1}},"children":[{"type":"text","value":"Stopping & Restarting the Kernel","position":{"start":{"line":1,"column":1},"end":{"line":1,"column":1}},"key":"O6YA71Hdls"}],"identifier":"stopping-restarting-the-kernel","label":"Stopping & Restarting the Kernel","html_id":"stopping-restarting-the-kernel","implicit":true,"key":"k0DQdRXNLR"},{"type":"paragraph","position":{"start":{"line":3,"column":1},"end":{"line":3,"column":1}},"children":[{"type":"text","value":"All of your commands and their output have been remembered by the kernel. However, sometimes you may get code that takes too long to execute, and you need to stop it. For example, in the next code cell, run:","position":{"start":{"line":3,"column":1},"end":{"line":3,"column":1}},"key":"aRl9GBvUpA"}],"key":"mgbc2ifu28"},{"type":"code","lang":"python","value":"time.sleep(1000)","position":{"start":{"line":5,"column":1},"end":{"line":7,"column":1}},"identifier":"sltxso0bnrhc-code","enumerator":"20","html_id":"sltxso0bnrhc-code","key":"XcpXuj41Fk"},{"type":"paragraph","position":{"start":{"line":9,"column":1},"end":{"line":9,"column":1}},"children":[{"type":"text","value":"You can stop the kernel with the square “stop” button at the top Notebook toolbar.  This results in a “KeyboardInterrupt” error.","position":{"start":{"line":9,"column":1},"end":{"line":9,"column":1}},"key":"cjSiVquZST"}],"key":"cxGLoxKrNs"},{"type":"paragraph","position":{"start":{"line":11,"column":1},"end":{"line":11,"column":1}},"children":[{"type":"text","value":"If you execute a notebook out of order, you can end up in a corrupted state (redefined variables, for example). To start fresh, you should restart the kernel with the circle-arrow button in the toolbar at the top. Now the kernel has forgotten everything, and you’ll need to rerun each cell.","position":{"start":{"line":11,"column":1},"end":{"line":11,"column":1}},"key":"mijRNh8h1a"}],"key":"mOQeVWomRM"}],"identifier":"sltxso0bnrhc","label":"SLtXSO0bNRHC","html_id":"sltxso0bnrhc","key":"FFaJvshHqy"},{"type":"block","kind":"notebook-content","data":{"id":"wdgosdLGNXtd"},"children":[{"type":"heading","depth":3,"position":{"start":{"line":1,"column":1},"end":{"line":1,"column":1}},"children":[{"type":"text","value":"Magics","position":{"start":{"line":1,"column":1},"end":{"line":1,"column":1}},"key":"HlUeaRcA7K"}],"identifier":"magics","label":"Magics","html_id":"magics","implicit":true,"key":"Vq5M5S81o5"},{"type":"paragraph","position":{"start":{"line":3,"column":1},"end":{"line":3,"column":1}},"children":[{"type":"text","value":"A “magic” is a Jupyter Notebook command proceded by a ","position":{"start":{"line":3,"column":1},"end":{"line":3,"column":1}},"key":"Y2AaZqDkVG"},{"type":"inlineCode","value":"%","position":{"start":{"line":3,"column":1},"end":{"line":3,"column":1}},"key":"ZQyVues4dJ"},{"type":"text","value":" symbol. In the next code cell, enter the following:","position":{"start":{"line":3,"column":1},"end":{"line":3,"column":1}},"key":"cSvwtU1shS"}],"key":"NOynGj9hUo"},{"type":"code","lang":"python","value":"%timeit time.sleep(1)","position":{"start":{"line":5,"column":1},"end":{"line":7,"column":1}},"identifier":"wdgosdlgnxtd-code-0","enumerator":"21","html_id":"wdgosdlgnxtd-code-0","key":"Uahehm8j19"},{"type":"paragraph","position":{"start":{"line":9,"column":1},"end":{"line":9,"column":1}},"children":[{"type":"text","value":"The “%timeit” magic is a timer that runs the command multiple times, measuring how long it takes and gathering timing statistics. Hit ","position":{"start":{"line":9,"column":1},"end":{"line":9,"column":1}},"key":"UKeKHAXh4Q"},{"type":"keyboard","children":[{"type":"text","value":"Shift","key":"BFQNBPB8kS"}],"key":"jj6jnJIK4N"},{"type":"text","value":"+","position":{"start":{"line":9,"column":1},"end":{"line":9,"column":1}},"key":"RUJgbKtH3s"},{"type":"keyboard","children":[{"type":"text","value":"Enter","key":"E5pZwhIjf9"}],"key":"b1QN2BEdzr"},{"type":"text","value":" to see it work.","position":{"start":{"line":9,"column":1},"end":{"line":9,"column":1}},"key":"tazNNQ6H6n"}],"key":"ipwJIGSNAN"},{"type":"paragraph","position":{"start":{"line":11,"column":1},"end":{"line":11,"column":1}},"children":[{"type":"text","value":"Multiline magics work on entire cells, and these have a double-","position":{"start":{"line":11,"column":1},"end":{"line":11,"column":1}},"key":"ZsN2cSz57P"},{"type":"inlineCode","value":"%","position":{"start":{"line":11,"column":1},"end":{"line":11,"column":1}},"key":"XALJNOtuve"},{"type":"text","value":".  For example, here is a multiline version of the timeit magic:","position":{"start":{"line":11,"column":1},"end":{"line":11,"column":1}},"key":"ZYlAxLZMsx"}],"key":"sDDxiHo8oY"},{"type":"code","lang":"python","value":"%%timeit\n\ntime.sleep(0.5)\ntime.sleep(0.5)","position":{"start":{"line":13,"column":1},"end":{"line":18,"column":1}},"identifier":"wdgosdlgnxtd-code-1","enumerator":"22","html_id":"wdgosdlgnxtd-code-1","key":"oBQFIZePPB"},{"type":"paragraph","position":{"start":{"line":20,"column":1},"end":{"line":20,"column":1}},"children":[{"type":"text","value":"Then press ","position":{"start":{"line":20,"column":1},"end":{"line":20,"column":1}},"key":"Fxurpg3tr5"},{"type":"keyboard","children":[{"type":"text","value":"Shift","key":"V7Un9yAMeo"}],"key":"ZHQJ7HpiFA"},{"type":"text","value":"+","position":{"start":{"line":20,"column":1},"end":{"line":20,"column":1}},"key":"UAa55CDDJl"},{"type":"keyboard","children":[{"type":"text","value":"Enter","key":"cITdKbnZ9q"}],"key":"SfHdLb0Orq"},{"type":"text","value":" to run it.  This will time the entire cell.","position":{"start":{"line":20,"column":1},"end":{"line":20,"column":1}},"key":"ocFiZGE9Db"}],"key":"OqnUlvIcB0"},{"type":"image","url":"/pythia-foundations/build/magics-0485a92c4eb9238ce82ed92997baf8a1.png","key":"d9woDPcujJ","urlSource":"../images/magics.png"}],"identifier":"wdgosdlgnxtd","label":"wdgosdLGNXtd","html_id":"wdgosdlgnxtd","key":"wBjb8JqxV3"},{"type":"block","kind":"notebook-content","data":{"id":"Y3euwtAoexvZ"},"children":[{"type":"heading","depth":2,"position":{"start":{"line":1,"column":1},"end":{"line":1,"column":1}},"children":[{"type":"text","value":"Shutting Down","position":{"start":{"line":1,"column":1},"end":{"line":1,"column":1}},"key":"NRMFWYkqOA"}],"identifier":"shutting-down","label":"Shutting Down","html_id":"shutting-down","implicit":true,"key":"gzQI9AaMXJ"},{"type":"paragraph","position":{"start":{"line":3,"column":1},"end":{"line":3,"column":1}},"children":[{"type":"text","value":"Before shutting down, save your notebook with the disc icon in the Notebook toolbar. Now, close both tabs (the notebook and the text editor). You’re back to the Launcher.","position":{"start":{"line":3,"column":1},"end":{"line":3,"column":1}},"key":"NcMJEwH5Je"}],"key":"M40X6mZh8p"},{"type":"paragraph","position":{"start":{"line":5,"column":1},"end":{"line":5,"column":1}},"children":[{"type":"text","value":"The notebook kernel is still running, though, so go to the Running Kernels tab and shut it down.","position":{"start":{"line":5,"column":1},"end":{"line":5,"column":1}},"key":"Xpkl50Y42W"}],"key":"XTlZMrY4zr"},{"type":"paragraph","position":{"start":{"line":7,"column":1},"end":{"line":7,"column":1}},"children":[{"type":"text","value":"Now we’re done.  Go to “File▶Shut Down” to close both your browser tab and JupyterLab itself.","position":{"start":{"line":7,"column":1},"end":{"line":7,"column":1}},"key":"eu6CPaIOVA"}],"key":"HXRk6HL9qT"}],"identifier":"y3euwtaoexvz","label":"Y3euwtAoexvZ","html_id":"y3euwtaoexvz","key":"RP1ivGNtJy"},{"type":"block","kind":"notebook-content","data":{"id":"Pp8SMkeLpfkf"},"children":[{"type":"heading","depth":2,"position":{"start":{"line":1,"column":1},"end":{"line":1,"column":1}},"children":[{"type":"text","value":"Summary","position":{"start":{"line":1,"column":1},"end":{"line":1,"column":1}},"key":"mjpCTLJt39"}],"identifier":"summary","label":"Summary","html_id":"summary","implicit":true,"key":"nOpPB0Fp8U"},{"type":"paragraph","position":{"start":{"line":3,"column":1},"end":{"line":3,"column":1}},"children":[{"type":"text","value":"You are now familiar with the JupyterLab interface and running Jupyter Notebooks. Jupyter is popular for allowing you to intersperse Markdown text or equations between code cells. Jupyter offers some functionality that a Python script does not: certain keyboard shortcuts, special variables, shell scripting, and magics.","position":{"start":{"line":3,"column":1},"end":{"line":3,"column":1}},"key":"Jyw5DYCCuO"}],"key":"xTwjCob69E"},{"type":"heading","depth":3,"position":{"start":{"line":5,"column":1},"end":{"line":5,"column":1}},"children":[{"type":"text","value":"What’s next?","position":{"start":{"line":5,"column":1},"end":{"line":5,"column":1}},"key":"bq7rdJCTsN"}],"identifier":"whats-next","label":"What’s next?","html_id":"whats-next","implicit":true,"key":"Tutpsd0eIE"},{"type":"list","ordered":false,"spread":false,"position":{"start":{"line":7,"column":1},"end":{"line":7,"column":1}},"children":[{"type":"listItem","spread":true,"position":{"start":{"line":7,"column":1},"end":{"line":7,"column":1}},"children":[{"type":"link","url":"/markdown","position":{"start":{"line":7,"column":1},"end":{"line":7,"column":1}},"children":[{"type":"text","value":"Markdown","position":{"start":{"line":7,"column":1},"end":{"line":7,"column":1}},"key":"YTrfwdLs03"}],"urlSource":"markdown","dataUrl":"/markdown.json","internal":true,"protocol":"file","key":"RQmc0brqNw"}],"key":"lZBmZYQ9XP"}],"key":"cIq678jiWK"}],"identifier":"pp8smkelpfkf","label":"Pp8SMkeLpfkf","html_id":"pp8smkelpfkf","key":"UREYlPjtnM"},{"type":"block","kind":"notebook-content","data":{"id":"lj8lTb4Aphra"},"children":[{"type":"heading","depth":2,"position":{"start":{"line":1,"column":1},"end":{"line":1,"column":1}},"children":[{"type":"text","value":"Resources and references","position":{"start":{"line":1,"column":1},"end":{"line":1,"column":1}},"key":"GmsXFFWYBr"}],"identifier":"resources-and-references","label":"Resources and references","html_id":"resources-and-references","implicit":true,"key":"qLha4ivfeP"},{"type":"list","ordered":false,"spread":false,"position":{"start":{"line":3,"column":1},"end":{"line":7,"column":1}},"children":[{"type":"listItem","spread":true,"position":{"start":{"line":3,"column":1},"end":{"line":3,"column":1}},"children":[{"type":"link","url":"https://jupyter.org/","position":{"start":{"line":3,"column":1},"end":{"line":3,"column":1}},"children":[{"type":"text","value":"Jupyter Documentation","position":{"start":{"line":3,"column":1},"end":{"line":3,"column":1}},"key":"XAoixzvKie"}],"urlSource":"https://jupyter.org/","key":"uo31x5zhjt"}],"key":"Oy4yeCn3ub"},{"type":"listItem","spread":true,"position":{"start":{"line":4,"column":1},"end":{"line":4,"column":1}},"children":[{"type":"link","url":"https://jupyterlab.readthedocs.io/en/stable/","position":{"start":{"line":4,"column":1},"end":{"line":4,"column":1}},"children":[{"type":"text","value":"JupyterLab Documentation","position":{"start":{"line":4,"column":1},"end":{"line":4,"column":1}},"key":"gX7BPCc5Hw"}],"urlSource":"https://jupyterlab.readthedocs.io/en/stable/","key":"a3sbkMd6eb"}],"key":"gHW2QcZHA8"},{"type":"listItem","spread":true,"position":{"start":{"line":5,"column":1},"end":{"line":5,"column":1}},"children":[{"type":"link","url":"https://jupyterlab.readthedocs.io/en/stable/user/extensions.html","position":{"start":{"line":5,"column":1},"end":{"line":5,"column":1}},"children":[{"type":"text","value":"JupyterLab Extensions","position":{"start":{"line":5,"column":1},"end":{"line":5,"column":1}},"key":"a71KrsYDDj"}],"urlSource":"https://jupyterlab.readthedocs.io/en/stable/user/extensions.html","key":"NfKEOcbvHR"}],"key":"igm9MCBogt"},{"type":"listItem","spread":true,"position":{"start":{"line":6,"column":1},"end":{"line":6,"column":1}},"children":[{"type":"link","url":"https://www.markdownguide.org/","position":{"start":{"line":6,"column":1},"end":{"line":6,"column":1}},"children":[{"type":"text","value":"Markdown Guide","position":{"start":{"line":6,"column":1},"end":{"line":6,"column":1}},"key":"UVMKarWurX"}],"urlSource":"https://www.markdownguide.org/","key":"oBfm0295kn"}],"key":"cktT2TdQep"},{"type":"listItem","spread":true,"position":{"start":{"line":7,"column":1},"end":{"line":7,"column":1}},"children":[{"type":"link","url":"https://youtu.be/xSzXvwzFsDU","position":{"start":{"line":7,"column":1},"end":{"line":7,"column":1}},"children":[{"type":"text","value":"Xdev Python Tutorial Seminar Series - Jupyter Notebooks","position":{"start":{"line":7,"column":1},"end":{"line":7,"column":1}},"key":"ctlOJinxYy"}],"urlSource":"https://youtu.be/xSzXvwzFsDU","key":"km56McHIsv"}],"key":"KxYyqbrv1n"}],"key":"PB3KNjjTCC"}],"identifier":"lj8ltb4aphra","label":"lj8lTb4Aphra","html_id":"lj8ltb4aphra","key":"EkvZFew7Az"}],"key":"w6ViS9AZfk"},"references":{"cite":{"order":[],"data":{}}},"footer":{"navigation":{"prev":{"title":"Getting Started with Jupyter","url":"/getting-started-jupyter","group":"Foundational skills"},"next":{"title":"Formatted Text in the Notebook with Markdown","url":"/markdown","group":"Foundational skills"}}},"domain":"http://localhost:3000"}